[
  {
    "decision_id": "SGD-2EE9B2EAE87363",
    "source_root_id": "SRC-ALL-PROJECTS",
    "project_id": "1110404",
    "family_id": "宇博實業",
    "relative_path": "111年度工作\\111年度工作\\111年度訂單(已完成)\\1110404宇博實業-芬園利民橋\\芬園鄉利民橋加壓站合約.xls",
    "file_name": "芬園鄉利民橋加壓站合約.xls",
    "file_id": "SRC-ALL-PROJECTS-FILE-190DB348A6DB",
    "sheet_id": "SRC-ALL-PROJECTS-FILE-190DB348A6DB-XLS-SHEET-001",
    "file_sha256": "ADE29E68377A07186EABB9CBB73E28AB7C7B8EAE28563AD8B9A709518FFF5347",
    "file_size": "180224",
    "workbook_format": "xls",
    "worksheet_name": "標單總表",
    "worksheet_visibility": "visible",
    "worksheet_fingerprint": "C89CF9B7601652B90BBF2968F9E200C9F9EA9B335AF72AFEE2CEA0E768F3B998",
    "workbook_sheet_count": 3,
    "detected_project_identifiers": [
      "1110404"
    ],
    "detected_customer_identifiers": [
      "宇博實業"
    ],
    "detected_document_role": "allowed_contract_workbook",
    "parser_name": "excel_com_legacy_xls",
    "parser_version": "16.0",
    "parse_status": "PARSED_WITH_FINGERPRINT",
    "formula_dependency_status": "NONE",
    "external_link_status": "NONE",
    "named_range_status": "NONE",
    "revision_status": "CURRENT_OR_UNKNOWN",
    "duplicate_or_supersession": "",
    "proposed_decision": "CANDIDATE",
    "final_decision": "UNREVIEWED",
    "reason_codes": [
      "CURRENT_PROJECT_ID_MATCH_REVIEWABLE",
      "LEGACY_XLS_PARSED_BY_EXCEL_COM_READ_ONLY",
      "MACROS_DISABLED"
    ],
    "evidence_references": [
      "SRC-ALL-PROJECTS-FILE-190DB348A6DB",
      "SRC-ALL-PROJECTS-FILE-190DB348A6DB-XLS-SHEET-001"
    ],
    "policy_version": "source_guard_policy_v2_autonomous_eval",
    "reviewer_or_approver": "",
    "decision_timestamp": "",
    "approval_manifest_hash": "",
    "sanitized_artifact_hash": "",
    "sanitized_csv_path": "manifests\\baseline-024\\source_candidates\\batch-002\\legacy_xls\\1110404\\legacy_xls_parse\\1110404\\SRC-ALL-PROJECTS-FILE-190DB348A6DB\\001_標單總表.csv",
    "sanitized_csv_sha256": "1889020535CEE44216FAE11071DDD48D16DA75CD013B2711D080C0703C6D2C31",
    "non_empty_rows": 13
  },
  {
    "decision_id": "SGD-65BE5B223BCC2B",
    "source_root_id": "SRC-ALL-PROJECTS",
    "project_id": "1110404",
    "family_id": "宇博實業",
    "relative_path": "111年度工作\\111年度工作\\111年度訂單(已完成)\\1110404宇博實業-芬園利民橋\\芬園鄉利民橋加壓站合約.xls",
    "file_name": "芬園鄉利民橋加壓站合約.xls",
    "file_id": "SRC-ALL-PROJECTS-FILE-190DB348A6DB",
    "sheet_id": "SRC-ALL-PROJECTS-FILE-190DB348A6DB-XLS-SHEET-002",
    "file_sha256": "ADE29E68377A07186EABB9CBB73E28AB7C7B8EAE28563AD8B9A709518FFF5347",
    "file_size": "180224",
    "workbook_format": "xls",
    "worksheet_name": "標單詳細表",
    "worksheet_visibility": "visible",
    "worksheet_fingerprint": "C0CDE51D1E4ABEBEF832698710823350A40D139D297F65F063EC92A9EF759712",
    "workbook_sheet_count": 3,
    "detected_project_identifiers": [
      "1110404"
    ],
    "detected_customer_identifiers": [
      "宇博實業"
    ],
    "detected_document_role": "allowed_contract_workbook",
    "parser_name": "excel_com_legacy_xls",
    "parser_version": "16.0",
    "parse_status": "PARSED_WITH_FINGERPRINT",
    "formula_dependency_status": "NONE",
    "external_link_status": "NONE",
    "named_range_status": "NONE",
    "revision_status": "CURRENT_OR_UNKNOWN",
    "duplicate_or_supersession": "",
    "proposed_decision": "CANDIDATE",
    "final_decision": "UNREVIEWED",
    "reason_codes": [
      "CURRENT_PROJECT_ID_MATCH_REVIEWABLE",
      "LEGACY_XLS_PARSED_BY_EXCEL_COM_READ_ONLY",
      "MACROS_DISABLED"
    ],
    "evidence_references": [
      "SRC-ALL-PROJECTS-FILE-190DB348A6DB",
      "SRC-ALL-PROJECTS-FILE-190DB348A6DB-XLS-SHEET-002"
    ],
    "policy_version": "source_guard_policy_v2_autonomous_eval",
    "reviewer_or_approver": "",
    "decision_timestamp": "",
    "approval_manifest_hash": "",
    "sanitized_artifact_hash": "",
    "sanitized_csv_path": "manifests\\baseline-024\\source_candidates\\batch-002\\legacy_xls\\1110404\\legacy_xls_parse\\1110404\\SRC-ALL-PROJECTS-FILE-190DB348A6DB\\002_標單詳細表.csv",
    "sanitized_csv_sha256": "42E69698B4CFD9D852D2318142E9CCD0F6570FCCC80AD6A67FA0186E88A4728F",
    "non_empty_rows": 151
  },
  {
    "decision_id": "SGD-6C707409E31450",
    "source_root_id": "SRC-ALL-PROJECTS",
    "project_id": "1110404",
    "family_id": "宇博實業",
    "relative_path": "111年度工作\\111年度工作\\111年度訂單(已完成)\\1110404宇博實業-芬園利民橋\\芬園鄉利民橋加壓站合約.xls",
    "file_name": "芬園鄉利民橋加壓站合約.xls",
    "file_id": "SRC-ALL-PROJECTS-FILE-190DB348A6DB",
    "sheet_id": "SRC-ALL-PROJECTS-FILE-190DB348A6DB-XLS-SHEET-003",
    "file_sha256": "ADE29E68377A07186EABB9CBB73E28AB7C7B8EAE28563AD8B9A709518FFF5347",
    "file_size": "180224",
    "workbook_format": "xls",
    "worksheet_name": "標單單價分析表",
    "worksheet_visibility": "visible",
    "worksheet_fingerprint": "CFAC7F10713C177C6B29DA7D0AE37695C7765F31CFFA6B853019808AFB3D23C4",
    "workbook_sheet_count": 3,
    "detected_project_identifiers": [
      "1110404"
    ],
    "detected_customer_identifiers": [
      "宇博實業"
    ],
    "detected_document_role": "allowed_contract_workbook",
    "parser_name": "excel_com_legacy_xls",
    "parser_version": "16.0",
    "parse_status": "PARSED_WITH_FINGERPRINT",
    "formula_dependency_status": "NONE",
    "external_link_status": "NONE",
    "named_range_status": "NONE",
    "revision_status": "CURRENT_OR_UNKNOWN",
    "duplicate_or_supersession": "",
    "proposed_decision": "CANDIDATE",
    "final_decision": "UNREVIEWED",
    "reason_codes": [
      "CURRENT_PROJECT_ID_MATCH_REVIEWABLE",
      "LEGACY_XLS_PARSED_BY_EXCEL_COM_READ_ONLY",
      "MACROS_DISABLED"
    ],
    "evidence_references": [
      "SRC-ALL-PROJECTS-FILE-190DB348A6DB",
      "SRC-ALL-PROJECTS-FILE-190DB348A6DB-XLS-SHEET-003"
    ],
    "policy_version": "source_guard_policy_v2_autonomous_eval",
    "reviewer_or_approver": "",
    "decision_timestamp": "",
    "approval_manifest_hash": "",
    "sanitized_artifact_hash": "",
    "sanitized_csv_path": "manifests\\baseline-024\\source_candidates\\batch-002\\legacy_xls\\1110404\\legacy_xls_parse\\1110404\\SRC-ALL-PROJECTS-FILE-190DB348A6DB\\003_標單單價分析表.csv",
    "sanitized_csv_sha256": "7F65541F680C82478CEA8BE575FD30DA9C5A62F2D50DD46A72A08A064CE3805A",
    "non_empty_rows": 630
  },
  {
    "decision_id": "SGD-A4E2A0C0C8171F",
    "source_root_id": "SRC-ALL-PROJECTS",
    "project_id": "1110404",
    "family_id": "宇博實業",
    "relative_path": "111年度工作\\111年度工作\\111年度訂單(已完成)\\1110404宇博實業-芬園利民橋\\芬園鄉利民橋加壓站材料清單.xls",
    "file_name": "芬園鄉利民橋加壓站材料清單.xls",
    "file_id": "SRC-ALL-PROJECTS-FILE-7213980F8162",
    "sheet_id": "SRC-ALL-PROJECTS-FILE-7213980F8162-XLS-SHEET-001",
    "file_sha256": "2B918C708B5BB33D8EE6EDF8EB8D87AA5E8EA57A60A8B1D04B0DA575369F8DCD",
    "file_size": "180224",
    "workbook_format": "xls",
    "worksheet_name": "標單總表",
    "worksheet_visibility": "visible",
    "worksheet_fingerprint": "C89CF9B7601652B90BBF2968F9E200C9F9EA9B335AF72AFEE2CEA0E768F3B998",
    "workbook_sheet_count": 3,
    "detected_project_identifiers": [
      "1110404"
    ],
    "detected_customer_identifiers": [
      "宇博實業"
    ],
    "detected_document_role": "allowed_material_list_workbook",
    "parser_name": "excel_com_legacy_xls",
    "parser_version": "16.0",
    "parse_status": "PARSED_WITH_FINGERPRINT",
    "formula_dependency_status": "NONE",
    "external_link_status": "NONE",
    "named_range_status": "NONE",
    "revision_status": "CURRENT_OR_UNKNOWN",
    "duplicate_or_supersession": "",
    "proposed_decision": "CANDIDATE",
    "final_decision": "UNREVIEWED",
    "reason_codes": [
      "CURRENT_PROJECT_ID_MATCH_REVIEWABLE",
      "LEGACY_XLS_PARSED_BY_EXCEL_COM_READ_ONLY",
      "MACROS_DISABLED"
    ],
    "evidence_references": [
      "SRC-ALL-PROJECTS-FILE-7213980F8162",
      "SRC-ALL-PROJECTS-FILE-7213980F8162-XLS-SHEET-001"
    ],
    "policy_version": "source_guard_policy_v2_autonomous_eval",
    "reviewer_or_approver": "",
    "decision_timestamp": "",
    "approval_manifest_hash": "",
    "sanitized_artifact_hash": "",
    "sanitized_csv_path": "manifests\\baseline-024\\source_candidates\\batch-002\\legacy_xls\\1110404\\legacy_xls_parse\\1110404\\SRC-ALL-PROJECTS-FILE-7213980F8162\\001_標單總表.csv",
    "sanitized_csv_sha256": "1889020535CEE44216FAE11071DDD48D16DA75CD013B2711D080C0703C6D2C31",
    "non_empty_rows": 13
  },
  {
    "decision_id": "SGD-559FC02EFE5929",
    "source_root_id": "SRC-ALL-PROJECTS",
    "project_id": "1110404",
    "family_id": "宇博實業",
    "relative_path": "111年度工作\\111年度工作\\111年度訂單(已完成)\\1110404宇博實業-芬園利民橋\\芬園鄉利民橋加壓站材料清單.xls",
    "file_name": "芬園鄉利民橋加壓站材料清單.xls",
    "file_id": "SRC-ALL-PROJECTS-FILE-7213980F8162",
    "sheet_id": "SRC-ALL-PROJECTS-FILE-7213980F8162-XLS-SHEET-002",
    "file_sha256": "2B918C708B5BB33D8EE6EDF8EB8D87AA5E8EA57A60A8B1D04B0DA575369F8DCD",
    "file_size": "180224",
    "workbook_format": "xls",
    "worksheet_name": "標單詳細表",
    "worksheet_visibility": "visible",
    "worksheet_fingerprint": "263B56476FCABD373F984F235BD4E5165C12A143A967B72AE4B81024D6410922",
    "workbook_sheet_count": 3,
    "detected_project_identifiers": [
      "1110404"
    ],
    "detected_customer_identifiers": [
      "宇博實業"
    ],
    "detected_document_role": "allowed_material_list_workbook",
    "parser_name": "excel_com_legacy_xls",
    "parser_version": "16.0",
    "parse_status": "PARSED_WITH_FINGERPRINT",
    "formula_dependency_status": "NONE",
    "external_link_status": "NONE",
    "named_range_status": "NONE",
    "revision_status": "CURRENT_OR_UNKNOWN",
    "duplicate_or_supersession": "",
    "proposed_decision": "CANDIDATE",
    "final_decision": "UNREVIEWED",
    "reason_codes": [
      "CURRENT_PROJECT_ID_MATCH_REVIEWABLE",
      "LEGACY_XLS_PARSED_BY_EXCEL_COM_READ_ONLY",
      "MACROS_DISABLED"
    ],
    "evidence_references": [
      "SRC-ALL-PROJECTS-FILE-7213980F8162",
      "SRC-ALL-PROJECTS-FILE-7213980F8162-XLS-SHEET-002"
    ],
    "policy_version": "source_guard_policy_v2_autonomous_eval",
    "reviewer_or_approver": "",
    "decision_timestamp": "",
    "approval_manifest_hash": "",
    "sanitized_artifact_hash": "",
    "sanitized_csv_path": "manifests\\baseline-024\\source_candidates\\batch-002\\legacy_xls\\1110404\\legacy_xls_parse\\1110404\\SRC-ALL-PROJECTS-FILE-7213980F8162\\002_標單詳細表.csv",
    "sanitized_csv_sha256": "F617C5E12589891F3329207EB9A43A89D079156ACCA48224EB9DD74F16FF3D7F",
    "non_empty_rows": 150
  },
  {
    "decision_id": "SGD-21B8EED7D73E16",
    "source_root_id": "SRC-ALL-PROJECTS",
    "project_id": "1110404",
    "family_id": "宇博實業",
    "relative_path": "111年度工作\\111年度工作\\111年度訂單(已完成)\\1110404宇博實業-芬園利民橋\\芬園鄉利民橋加壓站材料清單.xls",
    "file_name": "芬園鄉利民橋加壓站材料清單.xls",
    "file_id": "SRC-ALL-PROJECTS-FILE-7213980F8162",
    "sheet_id": "SRC-ALL-PROJECTS-FILE-7213980F8162-XLS-SHEET-003",
    "file_sha256": "2B918C708B5BB33D8EE6EDF8EB8D87AA5E8EA57A60A8B1D04B0DA575369F8DCD",
    "file_size": "180224",
    "workbook_format": "xls",
    "worksheet_name": "標單單價分析表",
    "worksheet_visibility": "visible",
    "worksheet_fingerprint": "CFAC7F10713C177C6B29DA7D0AE37695C7765F31CFFA6B853019808AFB3D23C4",
    "workbook_sheet_count": 3,
    "detected_project_identifiers": [
      "1110404"
    ],
    "detected_customer_identifiers": [
      "宇博實業"
    ],
    "detected_document_role": "allowed_material_list_workbook",
    "parser_name": "excel_com_legacy_xls",
    "parser_version": "16.0",
    "parse_status": "PARSED_WITH_FINGERPRINT",
    "formula_dependency_status": "NONE",
    "external_link_status": "NONE",
    "named_range_status": "NONE",
    "revision_status": "CURRENT_OR_UNKNOWN",
    "duplicate_or_supersession": "",
    "proposed_decision": "CANDIDATE",
    "final_decision": "UNREVIEWED",
    "reason_codes": [
      "CURRENT_PROJECT_ID_MATCH_REVIEWABLE",
      "LEGACY_XLS_PARSED_BY_EXCEL_COM_READ_ONLY",
      "MACROS_DISABLED"
    ],
    "evidence_references": [
      "SRC-ALL-PROJECTS-FILE-7213980F8162",
      "SRC-ALL-PROJECTS-FILE-7213980F8162-XLS-SHEET-003"
    ],
    "policy_version": "source_guard_policy_v2_autonomous_eval",
    "reviewer_or_approver": "",
    "decision_timestamp": "",
    "approval_manifest_hash": "",
    "sanitized_artifact_hash": "",
    "sanitized_csv_path": "manifests\\baseline-024\\source_candidates\\batch-002\\legacy_xls\\1110404\\legacy_xls_parse\\1110404\\SRC-ALL-PROJECTS-FILE-7213980F8162\\003_標單單價分析表.csv",
    "sanitized_csv_sha256": "7F65541F680C82478CEA8BE575FD30DA9C5A62F2D50DD46A72A08A064CE3805A",
    "non_empty_rows": 630
  },
  {
    "decision_id": "SGD-42E4F38C5B320E",
    "source_root_id": "SRC-ALL-PROJECTS",
    "project_id": "1110404",
    "family_id": "宇博實業",
    "relative_path": "111年度工作\\111年度工作\\111年度訂單(已完成)\\1110404宇博實業-芬園利民橋\\宇博彰化芬園鄉利民橋訂單分析表.xls",
    "file_name": "宇博彰化芬園鄉利民橋訂單分析表.xls",
    "file_id": "SRC-ALL-PROJECTS-FILE-969ACEDD72F3",
    "sheet_id": "SRC-ALL-PROJECTS-FILE-969ACEDD72F3-XLS-SHEET-001",
    "file_sha256": "966BC22278A067F5F04A07B94BEC259C46C5F8024AF771FDED1C5957A518293F",
    "file_size": "49152",
    "workbook_format": "xls",
    "worksheet_name": "Sheet2",
    "worksheet_visibility": "visible",
    "worksheet_fingerprint": "6E1F00A07BA73F8D4F7DB68596FEFD5B44486D4E3BBD87FFD9346354C946519A",
    "workbook_sheet_count": 3,
    "detected_project_identifiers": [
      "1110404"
    ],
    "detected_customer_identifiers": [
      "宇博實業"
    ],
    "detected_document_role": "spreadsheet_other",
    "parser_name": "excel_com_legacy_xls",
    "parser_version": "16.0",
    "parse_status": "PARSED_WITH_FINGERPRINT",
    "formula_dependency_status": "NONE",
    "external_link_status": "NONE",
    "named_range_status": "NONE",
    "revision_status": "CURRENT_OR_UNKNOWN",
    "duplicate_or_supersession": "",
    "proposed_decision": "CANDIDATE",
    "final_decision": "UNREVIEWED",
    "reason_codes": [
      "CURRENT_PROJECT_ID_MATCH_REVIEWABLE",
      "LEGACY_XLS_PARSED_BY_EXCEL_COM_READ_ONLY",
      "MACROS_DISABLED"
    ],
    "evidence_references": [
      "SRC-ALL-PROJECTS-FILE-969ACEDD72F3",
      "SRC-ALL-PROJECTS-FILE-969ACEDD72F3-XLS-SHEET-001"
    ],
    "policy_version": "source_guard_policy_v2_autonomous_eval",
    "reviewer_or_approver": "",
    "decision_timestamp": "",
    "approval_manifest_hash": "",
    "sanitized_artifact_hash": "",
    "sanitized_csv_path": "manifests\\baseline-024\\source_candidates\\batch-002\\legacy_xls\\1110404\\legacy_xls_parse\\1110404\\SRC-ALL-PROJECTS-FILE-969ACEDD72F3\\001_Sheet2.csv",
    "sanitized_csv_sha256": "6A6A91FE27EA88A24BB389BB41F1FD98692A5FB55DBB0C7DA9115656D2AB268D",
    "non_empty_rows": 29
  },
  {
    "decision_id": "SGD-316C6FFF77A62B",
    "source_root_id": "SRC-ALL-PROJECTS",
    "project_id": "1110404",
    "family_id": "宇博實業",
    "relative_path": "111年度工作\\111年度工作\\111年度訂單(已完成)\\1110404宇博實業-芬園利民橋\\宇博彰化芬園鄉利民橋訂單分析表.xls",
    "file_name": "宇博彰化芬園鄉利民橋訂單分析表.xls",
    "file_id": "SRC-ALL-PROJECTS-FILE-969ACEDD72F3",
    "sheet_id": "SRC-ALL-PROJECTS-FILE-969ACEDD72F3-XLS-SHEET-002",
    "file_sha256": "966BC22278A067F5F04A07B94BEC259C46C5F8024AF771FDED1C5957A518293F",
    "file_size": "49152",
    "workbook_format": "xls",
    "worksheet_name": "Sheet3",
    "worksheet_visibility": "visible",
    "worksheet_fingerprint": "54A7F3467D202254816CDDA76C992CF40888AD969355429892E7625654B0F933",
    "workbook_sheet_count": 3,
    "detected_project_identifiers": [
      "1110404"
    ],
    "detected_customer_identifiers": [
      "宇博實業"
    ],
    "detected_document_role": "spreadsheet_other",
    "parser_name": "excel_com_legacy_xls",
    "parser_version": "16.0",
    "parse_status": "PARSED_WITH_FINGERPRINT",
    "formula_dependency_status": "NONE",
    "external_link_status": "NONE",
    "named_range_status": "NONE",
    "revision_status": "CURRENT_OR_UNKNOWN",
    "duplicate_or_supersession": "",
    "proposed_decision": "CANDIDATE",
    "final_decision": "UNREVIEWED",
    "reason_codes": [
      "CURRENT_PROJECT_ID_MATCH_REVIEWABLE",
      "LEGACY_XLS_PARSED_BY_EXCEL_COM_READ_ONLY",
      "MACROS_DISABLED"
    ],
    "evidence_references": [
      "SRC-ALL-PROJECTS-FILE-969ACEDD72F3",
      "SRC-ALL-PROJECTS-FILE-969ACEDD72F3-XLS-SHEET-002"
    ],
    "policy_version": "source_guard_policy_v2_autonomous_eval",
    "reviewer_or_approver": "",
    "decision_timestamp": "",
    "approval_manifest_hash": "",
    "sanitized_artifact_hash": "",
    "sanitized_csv_path": "manifests\\baseline-024\\source_candidates\\batch-002\\legacy_xls\\1110404\\legacy_xls_parse\\1110404\\SRC-ALL-PROJECTS-FILE-969ACEDD72F3\\002_Sheet3.csv",
    "sanitized_csv_sha256": "F01A374E9C81E3DB89B3A42940C4D6A5447684986A1296E42BF13F196EED6295",
    "non_empty_rows": 0
  },
  {
    "decision_id": "SGD-99A73FC2696D5E",
    "source_root_id": "SRC-ALL-PROJECTS",
    "project_id": "1110404",
    "family_id": "宇博實業",
    "relative_path": "111年度工作\\111年度工作\\111年度訂單(已完成)\\1110404宇博實業-芬園利民橋\\宇博彰化芬園鄉利民橋訂單分析表.xls",
    "file_name": "宇博彰化芬園鄉利民橋訂單分析表.xls",
    "file_id": "SRC-ALL-PROJECTS-FILE-969ACEDD72F3",
    "sheet_id": "SRC-ALL-PROJECTS-FILE-969ACEDD72F3-XLS-SHEET-003",
    "file_sha256": "966BC22278A067F5F04A07B94BEC259C46C5F8024AF771FDED1C5957A518293F",
    "file_size": "49152",
    "workbook_format": "xls",
    "worksheet_name": "Sheet1",
    "worksheet_visibility": "visible",
    "worksheet_fingerprint": "D041E0793DF28BABB410316EB1776F89CA124C9C98B3B476B8B3A2A9A7C14D53",
    "workbook_sheet_count": 3,
    "detected_project_identifiers": [
      "1110404"
    ],
    "detected_customer_identifiers": [
      "宇博實業"
    ],
    "detected_document_role": "spreadsheet_other",
    "parser_name": "excel_com_legacy_xls",
    "parser_version": "16.0",
    "parse_status": "PARSED_WITH_FINGERPRINT",
    "formula_dependency_status": "NONE",
    "external_link_status": "NONE",
    "named_range_status": "NONE",
    "revision_status": "CURRENT_OR_UNKNOWN",
    "duplicate_or_supersession": "",
    "proposed_decision": "CANDIDATE",
    "final_decision": "UNREVIEWED",
    "reason_codes": [
      "CURRENT_PROJECT_ID_MATCH_REVIEWABLE",
      "LEGACY_XLS_PARSED_BY_EXCEL_COM_READ_ONLY",
      "MACROS_DISABLED"
    ],
    "evidence_references": [
      "SRC-ALL-PROJECTS-FILE-969ACEDD72F3",
      "SRC-ALL-PROJECTS-FILE-969ACEDD72F3-XLS-SHEET-003"
    ],
    "policy_version": "source_guard_policy_v2_autonomous_eval",
    "reviewer_or_approver": "",
    "decision_timestamp": "",
    "approval_manifest_hash": "",
    "sanitized_artifact_hash": "",
    "sanitized_csv_path": "manifests\\baseline-024\\source_candidates\\batch-002\\legacy_xls\\1110404\\legacy_xls_parse\\1110404\\SRC-ALL-PROJECTS-FILE-969ACEDD72F3\\003_Sheet1.csv",
    "sanitized_csv_sha256": "31BD7529380A0A14E3DC306931A380F889E02CDFB040DF5FDD4E8DA2A2D9BEBC",
    "non_empty_rows": 23
  },
  {
    "decision_id": "SGD-1E92D26A6909CA",
    "source_root_id": "SRC-ALL-PROJECTS",
    "project_id": "1110404",
    "family_id": "宇博實業",
    "relative_path": "111年度工作\\111年度工作\\111年度訂單(已完成)\\1110404宇博實業-芬園利民橋\\宇博彰化芬園鄉利民橋加壓站合約審查表.xls",
    "file_name": "宇博彰化芬園鄉利民橋加壓站合約審查表.xls",
    "file_id": "SRC-ALL-PROJECTS-FILE-9C7505CDBB38",
    "sheet_id": "SRC-ALL-PROJECTS-FILE-9C7505CDBB38-XLS-SHEET-001",
    "file_sha256": "BB4A8FECCA3D1ED14D54FA6F9A3D0885F34D63160F23C585F6A0955750306501",
    "file_size": "90112",
    "workbook_format": "xls",
    "worksheet_name": "分析表",
    "worksheet_visibility": "visible",
    "worksheet_fingerprint": "39A2693D6D07CFD0CF67C1FB98B893FD015E57ABD38AC3222EBE360C847D0486",
    "workbook_sheet_count": 3,
    "detected_project_identifiers": [
      "1110404"
    ],
    "detected_customer_identifiers": [
      "宇博實業"
    ],
    "detected_document_role": "allowed_contract_workbook",
    "parser_name": "excel_com_legacy_xls",
    "parser_version": "16.0",
    "parse_status": "PARSED_WITH_FINGERPRINT",
    "formula_dependency_status": "NONE",
    "external_link_status": "NONE",
    "named_range_status": "NAMED_RANGE_REVIEW_REQUIRED",
    "revision_status": "CURRENT_OR_UNKNOWN",
    "duplicate_or_supersession": "",
    "proposed_decision": "QUARANTINED",
    "final_decision": "UNREVIEWED",
    "reason_codes": [
      "CURRENT_PROJECT_ID_MATCH_REVIEWABLE",
      "LEGACY_XLS_PARSED_BY_EXCEL_COM_READ_ONLY",
      "MACROS_DISABLED",
      "NAMED_RANGE_PRESENT"
    ],
    "evidence_references": [
      "SRC-ALL-PROJECTS-FILE-9C7505CDBB38",
      "SRC-ALL-PROJECTS-FILE-9C7505CDBB38-XLS-SHEET-001"
    ],
    "policy_version": "source_guard_policy_v2_autonomous_eval",
    "reviewer_or_approver": "",
    "decision_timestamp": "",
    "approval_manifest_hash": "",
    "sanitized_artifact_hash": "",
    "sanitized_csv_path": "manifests\\baseline-024\\source_candidates\\batch-002\\legacy_xls\\1110404\\legacy_xls_parse\\1110404\\SRC-ALL-PROJECTS-FILE-9C7505CDBB38\\001_分析表.csv",
    "sanitized_csv_sha256": "C6C565F633620B16B5F812B1F089CA1598EC3DE4C63BE1684416CEF7E6E26E1B",
    "non_empty_rows": 13
  },
  {
    "decision_id": "SGD-9C44A25763284B",
    "source_root_id": "SRC-ALL-PROJECTS",
    "project_id": "1110404",
    "family_id": "宇博實業",
    "relative_path": "111年度工作\\111年度工作\\111年度訂單(已完成)\\1110404宇博實業-芬園利民橋\\宇博彰化芬園鄉利民橋加壓站合約審查表.xls",
    "file_name": "宇博彰化芬園鄉利民橋加壓站合約審查表.xls",
    "file_id": "SRC-ALL-PROJECTS-FILE-9C7505CDBB38",
    "sheet_id": "SRC-ALL-PROJECTS-FILE-9C7505CDBB38-XLS-SHEET-002",
    "file_sha256": "BB4A8FECCA3D1ED14D54FA6F9A3D0885F34D63160F23C585F6A0955750306501",
    "file_size": "90112",
    "workbook_format": "xls",
    "worksheet_name": "會議審查",
    "worksheet_visibility": "visible",
    "worksheet_fingerprint": "0C7BA3AF42DCD0CC3D5CBC997B323C9A239748E558246F1671FBC29E5E9556D9",
    "workbook_sheet_count": 3,
    "detected_project_identifiers": [
      "1110404"
    ],
    "detected_customer_identifiers": [
      "宇博實業"
    ],
    "detected_document_role": "allowed_contract_workbook",
    "parser_name": "excel_com_legacy_xls",
    "parser_version": "16.0",
    "parse_status": "PARSED_WITH_FINGERPRINT",
    "formula_dependency_status": "NONE",
    "external_link_status": "NONE",
    "named_range_status": "NAMED_RANGE_REVIEW_REQUIRED",
    "revision_status": "CURRENT_OR_UNKNOWN",
    "duplicate_or_supersession": "",
    "proposed_decision": "QUARANTINED",
    "final_decision": "UNREVIEWED",
    "reason_codes": [
      "CURRENT_PROJECT_ID_MATCH_REVIEWABLE",
      "LEGACY_XLS_PARSED_BY_EXCEL_COM_READ_ONLY",
      "MACROS_DISABLED",
      "NAMED_RANGE_PRESENT"
    ],
    "evidence_references": [
      "SRC-ALL-PROJECTS-FILE-9C7505CDBB38",
      "SRC-ALL-PROJECTS-FILE-9C7505CDBB38-XLS-SHEET-002"
    ],
    "policy_version": "source_guard_policy_v2_autonomous_eval",
    "reviewer_or_approver": "",
    "decision_timestamp": "",
    "approval_manifest_hash": "",
    "sanitized_artifact_hash": "",
    "sanitized_csv_path": "manifests\\baseline-024\\source_candidates\\batch-002\\legacy_xls\\1110404\\legacy_xls_parse\\1110404\\SRC-ALL-PROJECTS-FILE-9C7505CDBB38\\002_會議審查.csv",
    "sanitized_csv_sha256": "8F6DAA4201185E86ADEAF2AC6BEC543EDB3EB42FC8BFCF2CB9DCBA4E0B1C5B05",
    "non_empty_rows": 36
  },
  {
    "decision_id": "SGD-4A92E00143B376",
    "source_root_id": "SRC-ALL-PROJECTS",
    "project_id": "1110404",
    "family_id": "宇博實業",
    "relative_path": "111年度工作\\111年度工作\\111年度訂單(已完成)\\1110404宇博實業-芬園利民橋\\宇博彰化芬園鄉利民橋加壓站合約審查表.xls",
    "file_name": "宇博彰化芬園鄉利民橋加壓站合約審查表.xls",
    "file_id": "SRC-ALL-PROJECTS-FILE-9C7505CDBB38",
    "sheet_id": "SRC-ALL-PROJECTS-FILE-9C7505CDBB38-XLS-SHEET-003",
    "file_sha256": "BB4A8FECCA3D1ED14D54FA6F9A3D0885F34D63160F23C585F6A0955750306501",
    "file_size": "90112",
    "workbook_format": "xls",
    "worksheet_name": "Sheet3",
    "worksheet_visibility": "visible",
    "worksheet_fingerprint": "2431A7B5E34F6CDDF636CB6420EDAF96BB8F1E51757547FA6AD1B769DF2C82B2",
    "workbook_sheet_count": 3,
    "detected_project_identifiers": [
      "1110404"
    ],
    "detected_customer_identifiers": [
      "宇博實業"
    ],
    "detected_document_role": "allowed_contract_workbook",
    "parser_name": "excel_com_legacy_xls",
    "parser_version": "16.0",
    "parse_status": "PARSED_WITH_FINGERPRINT",
    "formula_dependency_status": "NONE",
    "external_link_status": "NONE",
    "named_range_status": "NAMED_RANGE_REVIEW_REQUIRED",
    "revision_status": "CURRENT_OR_UNKNOWN",
    "duplicate_or_supersession": "",
    "proposed_decision": "QUARANTINED",
    "final_decision": "UNREVIEWED",
    "reason_codes": [
      "CURRENT_PROJECT_ID_MATCH_REVIEWABLE",
      "LEGACY_XLS_PARSED_BY_EXCEL_COM_READ_ONLY",
      "MACROS_DISABLED",
      "NAMED_RANGE_PRESENT"
    ],
    "evidence_references": [
      "SRC-ALL-PROJECTS-FILE-9C7505CDBB38",
      "SRC-ALL-PROJECTS-FILE-9C7505CDBB38-XLS-SHEET-003"
    ],
    "policy_version": "source_guard_policy_v2_autonomous_eval",
    "reviewer_or_approver": "",
    "decision_timestamp": "",
    "approval_manifest_hash": "",
    "sanitized_artifact_hash": "",
    "sanitized_csv_path": "manifests\\baseline-024\\source_candidates\\batch-002\\legacy_xls\\1110404\\legacy_xls_parse\\1110404\\SRC-ALL-PROJECTS-FILE-9C7505CDBB38\\003_Sheet3.csv",
    "sanitized_csv_sha256": "F01A374E9C81E3DB89B3A42940C4D6A5447684986A1296E42BF13F196EED6295",
    "non_empty_rows": 0
  },
  {
    "decision_id": "SGD-DD318B0D6BDC85",
    "source_root_id": "SRC-ALL-PROJECTS",
    "project_id": "1110404",
    "family_id": "宇博實業",
    "relative_path": "111年度工作\\111年度工作\\111年度訂單(已完成)\\1110404宇博實業-芬園利民橋\\宇博彰化芬園鄉利民橋加壓站生產能力分析表.xls",
    "file_name": "宇博彰化芬園鄉利民橋加壓站生產能力分析表.xls",
    "file_id": "SRC-ALL-PROJECTS-FILE-BAE592ED9C3A",
    "sheet_id": "SRC-ALL-PROJECTS-FILE-BAE592ED9C3A-XLS-SHEET-001",
    "file_sha256": "976F802FF970BBE318FB2968310AB3A86C8804D08F9FA8255F9F9D1855743ED1",
    "file_size": "90112",
    "workbook_format": "xls",
    "worksheet_name": "分析表",
    "worksheet_visibility": "visible",
    "worksheet_fingerprint": "D82CF971A31DA4266E64495024A4FB5190441CB77EBF9472C69118F63D6144AC",
    "workbook_sheet_count": 3,
    "detected_project_identifiers": [
      "1110404"
    ],
    "detected_customer_identifiers": [
      "宇博實業"
    ],
    "detected_document_role": "spreadsheet_other",
    "parser_name": "excel_com_legacy_xls",
    "parser_version": "16.0",
    "parse_status": "PARSED_WITH_FINGERPRINT",
    "formula_dependency_status": "NONE",
    "external_link_status": "NONE",
    "named_range_status": "NAMED_RANGE_REVIEW_REQUIRED",
    "revision_status": "CURRENT_OR_UNKNOWN",
    "duplicate_or_supersession": "",
    "proposed_decision": "QUARANTINED",
    "final_decision": "UNREVIEWED",
    "reason_codes": [
      "CURRENT_PROJECT_ID_MATCH_REVIEWABLE",
      "LEGACY_XLS_PARSED_BY_EXCEL_COM_READ_ONLY",
      "MACROS_DISABLED",
      "NAMED_RANGE_PRESENT"
    ],
    "evidence_references": [
      "SRC-ALL-PROJECTS-FILE-BAE592ED9C3A",
      "SRC-ALL-PROJECTS-FILE-BAE592ED9C3A-XLS-SHEET-001"
    ],
    "policy_version": "source_guard_policy_v2_autonomous_eval",
    "reviewer_or_approver": "",
    "decision_timestamp": "",
    "approval_manifest_hash": "",
    "sanitized_artifact_hash": "",
    "sanitized_csv_path": "manifests\\baseline-024\\source_candidates\\batch-002\\legacy_xls\\1110404\\legacy_xls_parse\\1110404\\SRC-ALL-PROJECTS-FILE-BAE592ED9C3A\\001_分析表.csv",
    "sanitized_csv_sha256": "7B9CEC7A7519C9CAC405A6022D5E9FA3D9C1B600056F79D0D7189C5E927AF9A8",
    "non_empty_rows": 13
  },
  {
    "decision_id": "SGD-B4CC5F1F4D8000",
    "source_root_id": "SRC-ALL-PROJECTS",
    "project_id": "1110404",
    "family_id": "宇博實業",
    "relative_path": "111年度工作\\111年度工作\\111年度訂單(已完成)\\1110404宇博實業-芬園利民橋\\宇博彰化芬園鄉利民橋加壓站生產能力分析表.xls",
    "file_name": "宇博彰化芬園鄉利民橋加壓站生產能力分析表.xls",
    "file_id": "SRC-ALL-PROJECTS-FILE-BAE592ED9C3A",
    "sheet_id": "SRC-ALL-PROJECTS-FILE-BAE592ED9C3A-XLS-SHEET-002",
    "file_sha256": "976F802FF970BBE318FB2968310AB3A86C8804D08F9FA8255F9F9D1855743ED1",
    "file_size": "90112",
    "workbook_format": "xls",
    "worksheet_name": "會議審查",
    "worksheet_visibility": "visible",
    "worksheet_fingerprint": "BBDD1D43247C07456A401D1B6444FE071E20394B3AC154B26CC8CACF5E951DB9",
    "workbook_sheet_count": 3,
    "detected_project_identifiers": [
      "1110404"
    ],
    "detected_customer_identifiers": [
      "宇博實業"
    ],
    "detected_document_role": "spreadsheet_other",
    "parser_name": "excel_com_legacy_xls",
    "parser_version": "16.0",
    "parse_status": "PARSED_WITH_FINGERPRINT",
    "formula_dependency_status": "NONE",
    "external_link_status": "NONE",
    "named_range_status": "NAMED_RANGE_REVIEW_REQUIRED",
    "revision_status": "CURRENT_OR_UNKNOWN",
    "duplicate_or_supersession": "",
    "proposed_decision": "QUARANTINED",
    "final_decision": "UNREVIEWED",
    "reason_codes": [
      "CURRENT_PROJECT_ID_MATCH_REVIEWABLE",
      "LEGACY_XLS_PARSED_BY_EXCEL_COM_READ_ONLY",
      "MACROS_DISABLED",
      "NAMED_RANGE_PRESENT"
    ],
    "evidence_references": [
      "SRC-ALL-PROJECTS-FILE-BAE592ED9C3A",
      "SRC-ALL-PROJECTS-FILE-BAE592ED9C3A-XLS-SHEET-002"
    ],
    "policy_version": "source_guard_policy_v2_autonomous_eval",
    "reviewer_or_approver": "",
    "decision_timestamp": "",
    "approval_manifest_hash": "",
    "sanitized_artifact_hash": "",
    "sanitized_csv_path": "manifests\\baseline-024\\source_candidates\\batch-002\\legacy_xls\\1110404\\legacy_xls_parse\\1110404\\SRC-ALL-PROJECTS-FILE-BAE592ED9C3A\\002_會議審查.csv",
    "sanitized_csv_sha256": "BF5E8024BD17140B98959CDFFD7E6E18B8F04445B54F0AB6A425032B663F1D18",
    "non_empty_rows": 36
  },
  {
    "decision_id": "SGD-FBE04F7E5C1D9F",
    "source_root_id": "SRC-ALL-PROJECTS",
    "project_id": "1110404",
    "family_id": "宇博實業",
    "relative_path": "111年度工作\\111年度工作\\111年度訂單(已完成)\\1110404宇博實業-芬園利民橋\\宇博彰化芬園鄉利民橋加壓站生產能力分析表.xls",
    "file_name": "宇博彰化芬園鄉利民橋加壓站生產能力分析表.xls",
    "file_id": "SRC-ALL-PROJECTS-FILE-BAE592ED9C3A",
    "sheet_id": "SRC-ALL-PROJECTS-FILE-BAE592ED9C3A-XLS-SHEET-003",
    "file_sha256": "976F802FF970BBE318FB2968310AB3A86C8804D08F9FA8255F9F9D1855743ED1",
    "file_size": "90112",
    "workbook_format": "xls",
    "worksheet_name": "Sheet3",
    "worksheet_visibility": "visible",
    "worksheet_fingerprint": "2431A7B5E34F6CDDF636CB6420EDAF96BB8F1E51757547FA6AD1B769DF2C82B2",
    "workbook_sheet_count": 3,
    "detected_project_identifiers": [
      "1110404"
    ],
    "detected_customer_identifiers": [
      "宇博實業"
    ],
    "detected_document_role": "spreadsheet_other",
    "parser_name": "excel_com_legacy_xls",
    "parser_version": "16.0",
    "parse_status": "PARSED_WITH_FINGERPRINT",
    "formula_dependency_status": "NONE",
    "external_link_status": "NONE",
    "named_range_status": "NAMED_RANGE_REVIEW_REQUIRED",
    "revision_status": "CURRENT_OR_UNKNOWN",
    "duplicate_or_supersession": "",
    "proposed_decision": "QUARANTINED",
    "final_decision": "UNREVIEWED",
    "reason_codes": [
      "CURRENT_PROJECT_ID_MATCH_REVIEWABLE",
      "LEGACY_XLS_PARSED_BY_EXCEL_COM_READ_ONLY",
      "MACROS_DISABLED",
      "NAMED_RANGE_PRESENT"
    ],
    "evidence_references": [
      "SRC-ALL-PROJECTS-FILE-BAE592ED9C3A",
      "SRC-ALL-PROJECTS-FILE-BAE592ED9C3A-XLS-SHEET-003"
    ],
    "policy_version": "source_guard_policy_v2_autonomous_eval",
    "reviewer_or_approver": "",
    "decision_timestamp": "",
    "approval_manifest_hash": "",
    "sanitized_artifact_hash": "",
    "sanitized_csv_path": "manifests\\baseline-024\\source_candidates\\batch-002\\legacy_xls\\1110404\\legacy_xls_parse\\1110404\\SRC-ALL-PROJECTS-FILE-BAE592ED9C3A\\003_Sheet3.csv",
    "sanitized_csv_sha256": "F01A374E9C81E3DB89B3A42940C4D6A5447684986A1296E42BF13F196EED6295",
    "non_empty_rows": 0
  },
  {
    "decision_id": "SGD-154665F99F39D9",
    "source_root_id": "SRC-ALL-PROJECTS",
    "project_id": "1110404",
    "family_id": "宇博實業",
    "relative_path": "111年度工作\\111年度工作\\111年度訂單(已完成)\\1110404宇博實業-芬園利民橋\\宇博彰化芬園利民橋加壓站分項ls.xls",
    "file_name": "宇博彰化芬園利民橋加壓站分項ls.xls",
    "file_id": "SRC-ALL-PROJECTS-FILE-CA81957454CE",
    "sheet_id": "SRC-ALL-PROJECTS-FILE-CA81957454CE-XLS-SHEET-001",
    "file_sha256": "460ECF0ECB675D1D074665965459B57663D9B55FF25A1BB4356C135905A26A0A",
    "file_size": "31232",
    "workbook_format": "xls",
    "worksheet_name": "Sheet1",
    "worksheet_visibility": "visible",
    "worksheet_fingerprint": "04EDB5C3BE300BC47A0B02A868204E2332F009FC9FE0CED31484D66764ABA289",
    "workbook_sheet_count": 3,
    "detected_project_identifiers": [
      "1110404"
    ],
    "detected_customer_identifiers": [
      "宇博實業"
    ],
    "detected_document_role": "spreadsheet_other",
    "parser_name": "excel_com_legacy_xls",
    "parser_version": "16.0",
    "parse_status": "PARSED_WITH_FINGERPRINT",
    "formula_dependency_status": "NONE",
    "external_link_status": "NONE",
    "named_range_status": "NONE",
    "revision_status": "CURRENT_OR_UNKNOWN",
    "duplicate_or_supersession": "",
    "proposed_decision": "CANDIDATE",
    "final_decision": "UNREVIEWED",
    "reason_codes": [
      "CURRENT_PROJECT_ID_MATCH_REVIEWABLE",
      "LEGACY_XLS_PARSED_BY_EXCEL_COM_READ_ONLY",
      "MACROS_DISABLED"
    ],
    "evidence_references": [
      "SRC-ALL-PROJECTS-FILE-CA81957454CE",
      "SRC-ALL-PROJECTS-FILE-CA81957454CE-XLS-SHEET-001"
    ],
    "policy_version": "source_guard_policy_v2_autonomous_eval",
    "reviewer_or_approver": "",
    "decision_timestamp": "",
    "approval_manifest_hash": "",
    "sanitized_artifact_hash": "",
    "sanitized_csv_path": "manifests\\baseline-024\\source_candidates\\batch-002\\legacy_xls\\1110404\\legacy_xls_parse\\1110404\\SRC-ALL-PROJECTS-FILE-CA81957454CE\\001_Sheet1.csv",
    "sanitized_csv_sha256": "20B4D0698CC7597892A5EBC53723EBF26395FBB599C0149445983F38BF433F42",
    "non_empty_rows": 29
  },
  {
    "decision_id": "SGD-58743B0E288D2F",
    "source_root_id": "SRC-ALL-PROJECTS",
    "project_id": "1110404",
    "family_id": "宇博實業",
    "relative_path": "111年度工作\\111年度工作\\111年度訂單(已完成)\\1110404宇博實業-芬園利民橋\\宇博彰化芬園利民橋加壓站分項ls.xls",
    "file_name": "宇博彰化芬園利民橋加壓站分項ls.xls",
    "file_id": "SRC-ALL-PROJECTS-FILE-CA81957454CE",
    "sheet_id": "SRC-ALL-PROJECTS-FILE-CA81957454CE-XLS-SHEET-002",
    "file_sha256": "460ECF0ECB675D1D074665965459B57663D9B55FF25A1BB4356C135905A26A0A",
    "file_size": "31232",
    "workbook_format": "xls",
    "worksheet_name": "Sheet2",
    "worksheet_visibility": "visible",
    "worksheet_fingerprint": "2327F3E6ECEE912E215AF094F55DE408AB2C6FEEB3ABDC7FD50B51592DA9CE91",
    "workbook_sheet_count": 3,
    "detected_project_identifiers": [
      "1110404"
    ],
    "detected_customer_identifiers": [
      "宇博實業"
    ],
    "detected_document_role": "spreadsheet_other",
    "parser_name": "excel_com_legacy_xls",
    "parser_version": "16.0",
    "parse_status": "PARSED_WITH_FINGERPRINT",
    "formula_dependency_status": "NONE",
    "external_link_status": "NONE",
    "named_range_status": "NONE",
    "revision_status": "CURRENT_OR_UNKNOWN",
    "duplicate_or_supersession": "",
    "proposed_decision": "CANDIDATE",
    "final_decision": "UNREVIEWED",
    "reason_codes": [
      "CURRENT_PROJECT_ID_MATCH_REVIEWABLE",
      "LEGACY_XLS_PARSED_BY_EXCEL_COM_READ_ONLY",
      "MACROS_DISABLED"
    ],
    "evidence_references": [
      "SRC-ALL-PROJECTS-FILE-CA81957454CE",
      "SRC-ALL-PROJECTS-FILE-CA81957454CE-XLS-SHEET-002"
    ],
    "policy_version": "source_guard_policy_v2_autonomous_eval",
    "reviewer_or_approver": "",
    "decision_timestamp": "",
    "approval_manifest_hash": "",
    "sanitized_artifact_hash": "",
    "sanitized_csv_path": "manifests\\baseline-024\\source_candidates\\batch-002\\legacy_xls\\1110404\\legacy_xls_parse\\1110404\\SRC-ALL-PROJECTS-FILE-CA81957454CE\\002_Sheet2.csv",
    "sanitized_csv_sha256": "F01A374E9C81E3DB89B3A42940C4D6A5447684986A1296E42BF13F196EED6295",
    "non_empty_rows": 0
  },
  {
    "decision_id": "SGD-9FE56632926677",
    "source_root_id": "SRC-ALL-PROJECTS",
    "project_id": "1110404",
    "family_id": "宇博實業",
    "relative_path": "111年度工作\\111年度工作\\111年度訂單(已完成)\\1110404宇博實業-芬園利民橋\\宇博彰化芬園利民橋加壓站分項ls.xls",
    "file_name": "宇博彰化芬園利民橋加壓站分項ls.xls",
    "file_id": "SRC-ALL-PROJECTS-FILE-CA81957454CE",
    "sheet_id": "SRC-ALL-PROJECTS-FILE-CA81957454CE-XLS-SHEET-003",
    "file_sha256": "460ECF0ECB675D1D074665965459B57663D9B55FF25A1BB4356C135905A26A0A",
    "file_size": "31232",
    "workbook_format": "xls",
    "worksheet_name": "Sheet3",
    "worksheet_visibility": "visible",
    "worksheet_fingerprint": "54A7F3467D202254816CDDA76C992CF40888AD969355429892E7625654B0F933",
    "workbook_sheet_count": 3,
    "detected_project_identifiers": [
      "1110404"
    ],
    "detected_customer_identifiers": [
      "宇博實業"
    ],
    "detected_document_role": "spreadsheet_other",
    "parser_name": "excel_com_legacy_xls",
    "parser_version": "16.0",
    "parse_status": "PARSED_WITH_FINGERPRINT",
    "formula_dependency_status": "NONE",
    "external_link_status": "NONE",
    "named_range_status": "NONE",
    "revision_status": "CURRENT_OR_UNKNOWN",
    "duplicate_or_supersession": "",
    "proposed_decision": "CANDIDATE",
    "final_decision": "UNREVIEWED",
    "reason_codes": [
      "CURRENT_PROJECT_ID_MATCH_REVIEWABLE",
      "LEGACY_XLS_PARSED_BY_EXCEL_COM_READ_ONLY",
      "MACROS_DISABLED"
    ],
    "evidence_references": [
      "SRC-ALL-PROJECTS-FILE-CA81957454CE",
      "SRC-ALL-PROJECTS-FILE-CA81957454CE-XLS-SHEET-003"
    ],
    "policy_version": "source_guard_policy_v2_autonomous_eval",
    "reviewer_or_approver": "",
    "decision_timestamp": "",
    "approval_manifest_hash": "",
    "sanitized_artifact_hash": "",
    "sanitized_csv_path": "manifests\\baseline-024\\source_candidates\\batch-002\\legacy_xls\\1110404\\legacy_xls_parse\\1110404\\SRC-ALL-PROJECTS-FILE-CA81957454CE\\003_Sheet3.csv",
    "sanitized_csv_sha256": "F01A374E9C81E3DB89B3A42940C4D6A5447684986A1296E42BF13F196EED6295",
    "non_empty_rows": 0
  },
  {
    "decision_id": "SGD-41EF350A34D739",
    "source_root_id": "SRC-ALL-PROJECTS",
    "project_id": "1110404",
    "family_id": "宇博實業",
    "relative_path": "111年度工作\\111年度工作\\111年度訂單(已完成)\\1110404宇博實業-芬園利民橋\\工作記錄單宇博彰化芬園利民橋加壓站s.xls",
    "file_name": "工作記錄單宇博彰化芬園利民橋加壓站s.xls",
    "file_id": "SRC-ALL-PROJECTS-FILE-D2FD564B8814",
    "sheet_id": "SRC-ALL-PROJECTS-FILE-D2FD564B8814-XLS-SHEET-001",
    "file_sha256": "EC9EE04D8F60269FA08B2B18A186655F303B205B898A328A21BA26FD66D423D3",
    "file_size": "155136",
    "workbook_format": "xls",
    "worksheet_name": "0413",
    "worksheet_visibility": "visible",
    "worksheet_fingerprint": "44B250AE62DD3B0BC927C3C0EBF31D46567F1342287E2EFDFBA771BAAA7F9D65",
    "workbook_sheet_count": 6,
    "detected_project_identifiers": [
      "1110404"
    ],
    "detected_customer_identifiers": [
      "宇博實業"
    ],
    "detected_document_role": "spreadsheet_other",
    "parser_name": "excel_com_legacy_xls",
    "parser_version": "16.0",
    "parse_status": "PARSED_WITH_FINGERPRINT",
    "formula_dependency_status": "NONE",
    "external_link_status": "NONE",
    "named_range_status": "NAMED_RANGE_REVIEW_REQUIRED",
    "revision_status": "CURRENT_OR_UNKNOWN",
    "duplicate_or_supersession": "",
    "proposed_decision": "QUARANTINED",
    "final_decision": "UNREVIEWED",
    "reason_codes": [
      "CURRENT_PROJECT_ID_MATCH_REVIEWABLE",
      "LEGACY_XLS_PARSED_BY_EXCEL_COM_READ_ONLY",
      "MACROS_DISABLED",
      "NAMED_RANGE_PRESENT"
    ],
    "evidence_references": [
      "SRC-ALL-PROJECTS-FILE-D2FD564B8814",
      "SRC-ALL-PROJECTS-FILE-D2FD564B8814-XLS-SHEET-001"
    ],
    "policy_version": "source_guard_policy_v2_autonomous_eval",
    "reviewer_or_approver": "",
    "decision_timestamp": "",
    "approval_manifest_hash": "",
    "sanitized_artifact_hash": "",
    "sanitized_csv_path": "manifests\\baseline-024\\source_candidates\\batch-002\\legacy_xls\\1110404\\legacy_xls_parse\\1110404\\SRC-ALL-PROJECTS-FILE-D2FD564B8814\\001_0413.csv",
    "sanitized_csv_sha256": "AD0F33A7A0D4F68F87DCB8B78EF61DB3BC12674CC10FF4BB5F19DDA6868DAEA0",
    "non_empty_rows": 35
  },
  {
    "decision_id": "SGD-41C59E198051F5",
    "source_root_id": "SRC-ALL-PROJECTS",
    "project_id": "1110404",
    "family_id": "宇博實業",
    "relative_path": "111年度工作\\111年度工作\\111年度訂單(已完成)\\1110404宇博實業-芬園利民橋\\工作記錄單宇博彰化芬園利民橋加壓站s.xls",
    "file_name": "工作記錄單宇博彰化芬園利民橋加壓站s.xls",
    "file_id": "SRC-ALL-PROJECTS-FILE-D2FD564B8814",
    "sheet_id": "SRC-ALL-PROJECTS-FILE-D2FD564B8814-XLS-SHEET-002",
    "file_sha256": "EC9EE04D8F60269FA08B2B18A186655F303B205B898A328A21BA26FD66D423D3",
    "file_size": "155136",
    "workbook_format": "xls",
    "worksheet_name": "0415",
    "worksheet_visibility": "visible",
    "worksheet_fingerprint": "80F99AC9C6518B1C241192861715CA6A227CACBF8E8B08CB512EBB3C660380EC",
    "workbook_sheet_count": 6,
    "detected_project_identifiers": [
      "1110404"
    ],
    "detected_customer_identifiers": [
      "宇博實業"
    ],
    "detected_document_role": "spreadsheet_other",
    "parser_name": "excel_com_legacy_xls",
    "parser_version": "16.0",
    "parse_status": "PARSED_WITH_FINGERPRINT",
    "formula_dependency_status": "NONE",
    "external_link_status": "NONE",
    "named_range_status": "NAMED_RANGE_REVIEW_REQUIRED",
    "revision_status": "CURRENT_OR_UNKNOWN",
    "duplicate_or_supersession": "",
    "proposed_decision": "QUARANTINED",
    "final_decision": "UNREVIEWED",
    "reason_codes": [
      "CURRENT_PROJECT_ID_MATCH_REVIEWABLE",
      "LEGACY_XLS_PARSED_BY_EXCEL_COM_READ_ONLY",
      "MACROS_DISABLED",
      "NAMED_RANGE_PRESENT"
    ],
    "evidence_references": [
      "SRC-ALL-PROJECTS-FILE-D2FD564B8814",
      "SRC-ALL-PROJECTS-FILE-D2FD564B8814-XLS-SHEET-002"
    ],
    "policy_version": "source_guard_policy_v2_autonomous_eval",
    "reviewer_or_approver": "",
    "decision_timestamp": "",
    "approval_manifest_hash": "",
    "sanitized_artifact_hash": "",
    "sanitized_csv_path": "manifests\\baseline-024\\source_candidates\\batch-002\\legacy_xls\\1110404\\legacy_xls_parse\\1110404\\SRC-ALL-PROJECTS-FILE-D2FD564B8814\\002_0415.csv",
    "sanitized_csv_sha256": "85443C0FDC9678CCFB657AECCCB90A88F859E5FA16AB8B2EA7210B1053FE7B9A",
    "non_empty_rows": 35
  },
  {
    "decision_id": "SGD-311A2A3D5DBAD0",
    "source_root_id": "SRC-ALL-PROJECTS",
    "project_id": "1110404",
    "family_id": "宇博實業",
    "relative_path": "111年度工作\\111年度工作\\111年度訂單(已完成)\\1110404宇博實業-芬園利民橋\\工作記錄單宇博彰化芬園利民橋加壓站s.xls",
    "file_name": "工作記錄單宇博彰化芬園利民橋加壓站s.xls",
    "file_id": "SRC-ALL-PROJECTS-FILE-D2FD564B8814",
    "sheet_id": "SRC-ALL-PROJECTS-FILE-D2FD564B8814-XLS-SHEET-003",
    "file_sha256": "EC9EE04D8F60269FA08B2B18A186655F303B205B898A328A21BA26FD66D423D3",
    "file_size": "155136",
    "workbook_format": "xls",
    "worksheet_name": "空白",
    "worksheet_visibility": "visible",
    "worksheet_fingerprint": "B5AD89DF08DECDCE5F994AD3DA7C3BBEA1E45E17C3F9FE8E167667935B3A6262",
    "workbook_sheet_count": 6,
    "detected_project_identifiers": [
      "1110404"
    ],
    "detected_customer_identifiers": [
      "宇博實業"
    ],
    "detected_document_role": "spreadsheet_other",
    "parser_name": "excel_com_legacy_xls",
    "parser_version": "16.0",
    "parse_status": "PARSED_WITH_FINGERPRINT",
    "formula_dependency_status": "NONE",
    "external_link_status": "NONE",
    "named_range_status": "NAMED_RANGE_REVIEW_REQUIRED",
    "revision_status": "CURRENT_OR_UNKNOWN",
    "duplicate_or_supersession": "",
    "proposed_decision": "QUARANTINED",
    "final_decision": "UNREVIEWED",
    "reason_codes": [
      "CURRENT_PROJECT_ID_MATCH_REVIEWABLE",
      "LEGACY_XLS_PARSED_BY_EXCEL_COM_READ_ONLY",
      "MACROS_DISABLED",
      "NAMED_RANGE_PRESENT"
    ],
    "evidence_references": [
      "SRC-ALL-PROJECTS-FILE-D2FD564B8814",
      "SRC-ALL-PROJECTS-FILE-D2FD564B8814-XLS-SHEET-003"
    ],
    "policy_version": "source_guard_policy_v2_autonomous_eval",
    "reviewer_or_approver": "",
    "decision_timestamp": "",
    "approval_manifest_hash": "",
    "sanitized_artifact_hash": "",
    "sanitized_csv_path": "manifests\\baseline-024\\source_candidates\\batch-002\\legacy_xls\\1110404\\legacy_xls_parse\\1110404\\SRC-ALL-PROJECTS-FILE-D2FD564B8814\\003_空白.csv",
    "sanitized_csv_sha256": "1D9CD85BBEF8C721BBFD1971DE053612BFD9145A72AF191B7F8FFF5830E74A9D",
    "non_empty_rows": 35
  },
  {
    "decision_id": "SGD-7C4A3DEC7F2D75",
    "source_root_id": "SRC-ALL-PROJECTS",
    "project_id": "1110404",
    "family_id": "宇博實業",
    "relative_path": "111年度工作\\111年度工作\\111年度訂單(已完成)\\1110404宇博實業-芬園利民橋\\工作記錄單宇博彰化芬園利民橋加壓站s.xls",
    "file_name": "工作記錄單宇博彰化芬園利民橋加壓站s.xls",
    "file_id": "SRC-ALL-PROJECTS-FILE-D2FD564B8814",
    "sheet_id": "SRC-ALL-PROJECTS-FILE-D2FD564B8814-XLS-SHEET-004",
    "file_sha256": "EC9EE04D8F60269FA08B2B18A186655F303B205B898A328A21BA26FD66D423D3",
    "file_size": "155136",
    "workbook_format": "xls",
    "worksheet_name": "05",
    "worksheet_visibility": "visible",
    "worksheet_fingerprint": "C486E895C071C0C972EC1931CBA0899016DCFC94173F74D32DAB9D6E9DFCD142",
    "workbook_sheet_count": 6,
    "detected_project_identifiers": [
      "1110404"
    ],
    "detected_customer_identifiers": [
      "宇博實業"
    ],
    "detected_document_role": "spreadsheet_other",
    "parser_name": "excel_com_legacy_xls",
    "parser_version": "16.0",
    "parse_status": "PARSED_WITH_FINGERPRINT",
    "formula_dependency_status": "NONE",
    "external_link_status": "NONE",
    "named_range_status": "NAMED_RANGE_REVIEW_REQUIRED",
    "revision_status": "CURRENT_OR_UNKNOWN",
    "duplicate_or_supersession": "",
    "proposed_decision": "QUARANTINED",
    "final_decision": "UNREVIEWED",
    "reason_codes": [
      "CURRENT_PROJECT_ID_MATCH_REVIEWABLE",
      "LEGACY_XLS_PARSED_BY_EXCEL_COM_READ_ONLY",
      "MACROS_DISABLED",
      "NAMED_RANGE_PRESENT"
    ],
    "evidence_references": [
      "SRC-ALL-PROJECTS-FILE-D2FD564B8814",
      "SRC-ALL-PROJECTS-FILE-D2FD564B8814-XLS-SHEET-004"
    ],
    "policy_version": "source_guard_policy_v2_autonomous_eval",
    "reviewer_or_approver": "",
    "decision_timestamp": "",
    "approval_manifest_hash": "",
    "sanitized_artifact_hash": "",
    "sanitized_csv_path": "manifests\\baseline-024\\source_candidates\\batch-002\\legacy_xls\\1110404\\legacy_xls_parse\\1110404\\SRC-ALL-PROJECTS-FILE-D2FD564B8814\\004_05.csv",
    "sanitized_csv_sha256": "768EF9E29A9A541E53DBA9A61496CBC5EA46A9498F86F833F1E0BEB02A18C41C",
    "non_empty_rows": 35
  },
  {
    "decision_id": "SGD-A9E0910F377360",
    "source_root_id": "SRC-ALL-PROJECTS",
    "project_id": "1110404",
    "family_id": "宇博實業",
    "relative_path": "111年度工作\\111年度工作\\111年度訂單(已完成)\\1110404宇博實業-芬園利民橋\\工作記錄單宇博彰化芬園利民橋加壓站s.xls",
    "file_name": "工作記錄單宇博彰化芬園利民橋加壓站s.xls",
    "file_id": "SRC-ALL-PROJECTS-FILE-D2FD564B8814",
    "sheet_id": "SRC-ALL-PROJECTS-FILE-D2FD564B8814-XLS-SHEET-005",
    "file_sha256": "EC9EE04D8F60269FA08B2B18A186655F303B205B898A328A21BA26FD66D423D3",
    "file_size": "155136",
    "workbook_format": "xls",
    "worksheet_name": "05 (2)",
    "worksheet_visibility": "visible",
    "worksheet_fingerprint": "AB9BB32E176B865C84DBA725CE82266BEFF1495F0C2BAF3232E972E6C74BD8B2",
    "workbook_sheet_count": 6,
    "detected_project_identifiers": [
      "1110404"
    ],
    "detected_customer_identifiers": [
      "宇博實業"
    ],
    "detected_document_role": "spreadsheet_other",
    "parser_name": "excel_com_legacy_xls",
    "parser_version": "16.0",
    "parse_status": "PARSED_WITH_FINGERPRINT",
    "formula_dependency_status": "NONE",
    "external_link_status": "NONE",
    "named_range_status": "NAMED_RANGE_REVIEW_REQUIRED",
    "revision_status": "CURRENT_OR_UNKNOWN",
    "duplicate_or_supersession": "",
    "proposed_decision": "QUARANTINED",
    "final_decision": "UNREVIEWED",
    "reason_codes": [
      "CURRENT_PROJECT_ID_MATCH_REVIEWABLE",
      "LEGACY_XLS_PARSED_BY_EXCEL_COM_READ_ONLY",
      "MACROS_DISABLED",
      "NAMED_RANGE_PRESENT"
    ],
    "evidence_references": [
      "SRC-ALL-PROJECTS-FILE-D2FD564B8814",
      "SRC-ALL-PROJECTS-FILE-D2FD564B8814-XLS-SHEET-005"
    ],
    "policy_version": "source_guard_policy_v2_autonomous_eval",
    "reviewer_or_approver": "",
    "decision_timestamp": "",
    "approval_manifest_hash": "",
    "sanitized_artifact_hash": "",
    "sanitized_csv_path": "manifests\\baseline-024\\source_candidates\\batch-002\\legacy_xls\\1110404\\legacy_xls_parse\\1110404\\SRC-ALL-PROJECTS-FILE-D2FD564B8814\\005_05 (2).csv",
    "sanitized_csv_sha256": "AD46148889E6540EA6AC05F9BEE96AC0C92B5655F2025D70C3192CBEA5ED1990",
    "non_empty_rows": 35
  },
  {
    "decision_id": "SGD-10AC93C56877A3",
    "source_root_id": "SRC-ALL-PROJECTS",
    "project_id": "1110404",
    "family_id": "宇博實業",
    "relative_path": "111年度工作\\111年度工作\\111年度訂單(已完成)\\1110404宇博實業-芬園利民橋\\工作記錄單宇博彰化芬園利民橋加壓站s.xls",
    "file_name": "工作記錄單宇博彰化芬園利民橋加壓站s.xls",
    "file_id": "SRC-ALL-PROJECTS-FILE-D2FD564B8814",
    "sheet_id": "SRC-ALL-PROJECTS-FILE-D2FD564B8814-XLS-SHEET-006",
    "file_sha256": "EC9EE04D8F60269FA08B2B18A186655F303B205B898A328A21BA26FD66D423D3",
    "file_size": "155136",
    "workbook_format": "xls",
    "worksheet_name": "0505",
    "worksheet_visibility": "visible",
    "worksheet_fingerprint": "37D59563AEC62339E44CB44F1CDCF9876664CAEA847C43C2B551E73D1ADA7D27",
    "workbook_sheet_count": 6,
    "detected_project_identifiers": [
      "1110404"
    ],
    "detected_customer_identifiers": [
      "宇博實業"
    ],
    "detected_document_role": "spreadsheet_other",
    "parser_name": "excel_com_legacy_xls",
    "parser_version": "16.0",
    "parse_status": "PARSED_WITH_FINGERPRINT",
    "formula_dependency_status": "NONE",
    "external_link_status": "NONE",
    "named_range_status": "NAMED_RANGE_REVIEW_REQUIRED",
    "revision_status": "CURRENT_OR_UNKNOWN",
    "duplicate_or_supersession": "",
    "proposed_decision": "QUARANTINED",
    "final_decision": "UNREVIEWED",
    "reason_codes": [
      "CURRENT_PROJECT_ID_MATCH_REVIEWABLE",
      "LEGACY_XLS_PARSED_BY_EXCEL_COM_READ_ONLY",
      "MACROS_DISABLED",
      "NAMED_RANGE_PRESENT"
    ],
    "evidence_references": [
      "SRC-ALL-PROJECTS-FILE-D2FD564B8814",
      "SRC-ALL-PROJECTS-FILE-D2FD564B8814-XLS-SHEET-006"
    ],
    "policy_version": "source_guard_policy_v2_autonomous_eval",
    "reviewer_or_approver": "",
    "decision_timestamp": "",
    "approval_manifest_hash": "",
    "sanitized_artifact_hash": "",
    "sanitized_csv_path": "manifests\\baseline-024\\source_candidates\\batch-002\\legacy_xls\\1110404\\legacy_xls_parse\\1110404\\SRC-ALL-PROJECTS-FILE-D2FD564B8814\\006_0505.csv",
    "sanitized_csv_sha256": "C0352E26D0F4EE77DD0B489F81E53A5CF110A21A5D88AD1BA9150A7069BA6E27",
    "non_empty_rows": 29
  }
]
