{
  "project_id": "1110404",
  "policy_version": "source_guard_policy_v2_autonomous_eval",
  "reviewable_items": [
    {
      "decision_id": "SGD-2EE9B2EAE87363",
      "file_id": "SRC-ALL-PROJECTS-FILE-190DB348A6DB",
      "sheet_id": "SRC-ALL-PROJECTS-FILE-190DB348A6DB-XLS-SHEET-001",
      "project_id": "1110404",
      "relative_path": "111年度工作\\111年度工作\\111年度訂單(已完成)\\1110404宇博實業-芬園利民橋\\芬園鄉利民橋加壓站合約.xls",
      "detected_document_role": "allowed_contract_workbook",
      "file_sha256": "ADE29E68377A07186EABB9CBB73E28AB7C7B8EAE28563AD8B9A709518FFF5347",
      "worksheet_name": "標單總表",
      "worksheet_visibility": "visible",
      "worksheet_fingerprint": "C89CF9B7601652B90BBF2968F9E200C9F9EA9B335AF72AFEE2CEA0E768F3B998",
      "proposed_decision": "CANDIDATE",
      "prefilter_state": "SUBMIT_TO_REVIEW",
      "reason_codes": [
        "CURRENT_PROJECT_ID_MATCH_REVIEWABLE",
        "LEGACY_XLS_PARSED_BY_EXCEL_COM_READ_ONLY",
        "MACROS_DISABLED"
      ],
      "checks": [
        {
          "check": "source_root",
          "status": "PASS",
          "evidence": "SRC-ALL-PROJECTS"
        },
        {
          "check": "file_sha256",
          "status": "PASS",
          "evidence": "ADE29E68377A07186EABB9CBB73E28AB7C7B8EAE28563AD8B9A709518FFF5347"
        },
        {
          "check": "legacy_xls_parser_stability",
          "status": "PASS",
          "evidence": "excel_com_legacy_xls_v1"
        },
        {
          "check": "worksheet_fingerprint",
          "status": "PASS",
          "evidence": "C89CF9B7601652B90BBF2968F9E200C9F9EA9B335AF72AFEE2CEA0E768F3B998"
        }
      ],
      "reviewable": true
    },
    {
      "decision_id": "SGD-65BE5B223BCC2B",
      "file_id": "SRC-ALL-PROJECTS-FILE-190DB348A6DB",
      "sheet_id": "SRC-ALL-PROJECTS-FILE-190DB348A6DB-XLS-SHEET-002",
      "project_id": "1110404",
      "relative_path": "111年度工作\\111年度工作\\111年度訂單(已完成)\\1110404宇博實業-芬園利民橋\\芬園鄉利民橋加壓站合約.xls",
      "detected_document_role": "allowed_contract_workbook",
      "file_sha256": "ADE29E68377A07186EABB9CBB73E28AB7C7B8EAE28563AD8B9A709518FFF5347",
      "worksheet_name": "標單詳細表",
      "worksheet_visibility": "visible",
      "worksheet_fingerprint": "C0CDE51D1E4ABEBEF832698710823350A40D139D297F65F063EC92A9EF759712",
      "proposed_decision": "CANDIDATE",
      "prefilter_state": "SUBMIT_TO_REVIEW",
      "reason_codes": [
        "CURRENT_PROJECT_ID_MATCH_REVIEWABLE",
        "LEGACY_XLS_PARSED_BY_EXCEL_COM_READ_ONLY",
        "MACROS_DISABLED"
      ],
      "checks": [
        {
          "check": "source_root",
          "status": "PASS",
          "evidence": "SRC-ALL-PROJECTS"
        },
        {
          "check": "file_sha256",
          "status": "PASS",
          "evidence": "ADE29E68377A07186EABB9CBB73E28AB7C7B8EAE28563AD8B9A709518FFF5347"
        },
        {
          "check": "legacy_xls_parser_stability",
          "status": "PASS",
          "evidence": "excel_com_legacy_xls_v1"
        },
        {
          "check": "worksheet_fingerprint",
          "status": "PASS",
          "evidence": "C0CDE51D1E4ABEBEF832698710823350A40D139D297F65F063EC92A9EF759712"
        }
      ],
      "reviewable": true
    },
    {
      "decision_id": "SGD-6C707409E31450",
      "file_id": "SRC-ALL-PROJECTS-FILE-190DB348A6DB",
      "sheet_id": "SRC-ALL-PROJECTS-FILE-190DB348A6DB-XLS-SHEET-003",
      "project_id": "1110404",
      "relative_path": "111年度工作\\111年度工作\\111年度訂單(已完成)\\1110404宇博實業-芬園利民橋\\芬園鄉利民橋加壓站合約.xls",
      "detected_document_role": "allowed_contract_workbook",
      "file_sha256": "ADE29E68377A07186EABB9CBB73E28AB7C7B8EAE28563AD8B9A709518FFF5347",
      "worksheet_name": "標單單價分析表",
      "worksheet_visibility": "visible",
      "worksheet_fingerprint": "CFAC7F10713C177C6B29DA7D0AE37695C7765F31CFFA6B853019808AFB3D23C4",
      "proposed_decision": "CANDIDATE",
      "prefilter_state": "SUBMIT_TO_REVIEW",
      "reason_codes": [
        "CURRENT_PROJECT_ID_MATCH_REVIEWABLE",
        "LEGACY_XLS_PARSED_BY_EXCEL_COM_READ_ONLY",
        "MACROS_DISABLED"
      ],
      "checks": [
        {
          "check": "source_root",
          "status": "PASS",
          "evidence": "SRC-ALL-PROJECTS"
        },
        {
          "check": "file_sha256",
          "status": "PASS",
          "evidence": "ADE29E68377A07186EABB9CBB73E28AB7C7B8EAE28563AD8B9A709518FFF5347"
        },
        {
          "check": "legacy_xls_parser_stability",
          "status": "PASS",
          "evidence": "excel_com_legacy_xls_v1"
        },
        {
          "check": "worksheet_fingerprint",
          "status": "PASS",
          "evidence": "CFAC7F10713C177C6B29DA7D0AE37695C7765F31CFFA6B853019808AFB3D23C4"
        }
      ],
      "reviewable": true
    },
    {
      "decision_id": "SGD-A4E2A0C0C8171F",
      "file_id": "SRC-ALL-PROJECTS-FILE-7213980F8162",
      "sheet_id": "SRC-ALL-PROJECTS-FILE-7213980F8162-XLS-SHEET-001",
      "project_id": "1110404",
      "relative_path": "111年度工作\\111年度工作\\111年度訂單(已完成)\\1110404宇博實業-芬園利民橋\\芬園鄉利民橋加壓站材料清單.xls",
      "detected_document_role": "allowed_material_list_workbook",
      "file_sha256": "2B918C708B5BB33D8EE6EDF8EB8D87AA5E8EA57A60A8B1D04B0DA575369F8DCD",
      "worksheet_name": "標單總表",
      "worksheet_visibility": "visible",
      "worksheet_fingerprint": "C89CF9B7601652B90BBF2968F9E200C9F9EA9B335AF72AFEE2CEA0E768F3B998",
      "proposed_decision": "CANDIDATE",
      "prefilter_state": "SUBMIT_TO_REVIEW",
      "reason_codes": [
        "CURRENT_PROJECT_ID_MATCH_REVIEWABLE",
        "LEGACY_XLS_PARSED_BY_EXCEL_COM_READ_ONLY",
        "MACROS_DISABLED"
      ],
      "checks": [
        {
          "check": "source_root",
          "status": "PASS",
          "evidence": "SRC-ALL-PROJECTS"
        },
        {
          "check": "file_sha256",
          "status": "PASS",
          "evidence": "2B918C708B5BB33D8EE6EDF8EB8D87AA5E8EA57A60A8B1D04B0DA575369F8DCD"
        },
        {
          "check": "legacy_xls_parser_stability",
          "status": "PASS",
          "evidence": "excel_com_legacy_xls_v1"
        },
        {
          "check": "worksheet_fingerprint",
          "status": "PASS",
          "evidence": "C89CF9B7601652B90BBF2968F9E200C9F9EA9B335AF72AFEE2CEA0E768F3B998"
        }
      ],
      "reviewable": true
    },
    {
      "decision_id": "SGD-559FC02EFE5929",
      "file_id": "SRC-ALL-PROJECTS-FILE-7213980F8162",
      "sheet_id": "SRC-ALL-PROJECTS-FILE-7213980F8162-XLS-SHEET-002",
      "project_id": "1110404",
      "relative_path": "111年度工作\\111年度工作\\111年度訂單(已完成)\\1110404宇博實業-芬園利民橋\\芬園鄉利民橋加壓站材料清單.xls",
      "detected_document_role": "allowed_material_list_workbook",
      "file_sha256": "2B918C708B5BB33D8EE6EDF8EB8D87AA5E8EA57A60A8B1D04B0DA575369F8DCD",
      "worksheet_name": "標單詳細表",
      "worksheet_visibility": "visible",
      "worksheet_fingerprint": "263B56476FCABD373F984F235BD4E5165C12A143A967B72AE4B81024D6410922",
      "proposed_decision": "CANDIDATE",
      "prefilter_state": "SUBMIT_TO_REVIEW",
      "reason_codes": [
        "CURRENT_PROJECT_ID_MATCH_REVIEWABLE",
        "LEGACY_XLS_PARSED_BY_EXCEL_COM_READ_ONLY",
        "MACROS_DISABLED"
      ],
      "checks": [
        {
          "check": "source_root",
          "status": "PASS",
          "evidence": "SRC-ALL-PROJECTS"
        },
        {
          "check": "file_sha256",
          "status": "PASS",
          "evidence": "2B918C708B5BB33D8EE6EDF8EB8D87AA5E8EA57A60A8B1D04B0DA575369F8DCD"
        },
        {
          "check": "legacy_xls_parser_stability",
          "status": "PASS",
          "evidence": "excel_com_legacy_xls_v1"
        },
        {
          "check": "worksheet_fingerprint",
          "status": "PASS",
          "evidence": "263B56476FCABD373F984F235BD4E5165C12A143A967B72AE4B81024D6410922"
        }
      ],
      "reviewable": true
    },
    {
      "decision_id": "SGD-21B8EED7D73E16",
      "file_id": "SRC-ALL-PROJECTS-FILE-7213980F8162",
      "sheet_id": "SRC-ALL-PROJECTS-FILE-7213980F8162-XLS-SHEET-003",
      "project_id": "1110404",
      "relative_path": "111年度工作\\111年度工作\\111年度訂單(已完成)\\1110404宇博實業-芬園利民橋\\芬園鄉利民橋加壓站材料清單.xls",
      "detected_document_role": "allowed_material_list_workbook",
      "file_sha256": "2B918C708B5BB33D8EE6EDF8EB8D87AA5E8EA57A60A8B1D04B0DA575369F8DCD",
      "worksheet_name": "標單單價分析表",
      "worksheet_visibility": "visible",
      "worksheet_fingerprint": "CFAC7F10713C177C6B29DA7D0AE37695C7765F31CFFA6B853019808AFB3D23C4",
      "proposed_decision": "CANDIDATE",
      "prefilter_state": "SUBMIT_TO_REVIEW",
      "reason_codes": [
        "CURRENT_PROJECT_ID_MATCH_REVIEWABLE",
        "LEGACY_XLS_PARSED_BY_EXCEL_COM_READ_ONLY",
        "MACROS_DISABLED"
      ],
      "checks": [
        {
          "check": "source_root",
          "status": "PASS",
          "evidence": "SRC-ALL-PROJECTS"
        },
        {
          "check": "file_sha256",
          "status": "PASS",
          "evidence": "2B918C708B5BB33D8EE6EDF8EB8D87AA5E8EA57A60A8B1D04B0DA575369F8DCD"
        },
        {
          "check": "legacy_xls_parser_stability",
          "status": "PASS",
          "evidence": "excel_com_legacy_xls_v1"
        },
        {
          "check": "worksheet_fingerprint",
          "status": "PASS",
          "evidence": "CFAC7F10713C177C6B29DA7D0AE37695C7765F31CFFA6B853019808AFB3D23C4"
        }
      ],
      "reviewable": true
    },
    {
      "decision_id": "SGD-42E4F38C5B320E",
      "file_id": "SRC-ALL-PROJECTS-FILE-969ACEDD72F3",
      "sheet_id": "SRC-ALL-PROJECTS-FILE-969ACEDD72F3-XLS-SHEET-001",
      "project_id": "1110404",
      "relative_path": "111年度工作\\111年度工作\\111年度訂單(已完成)\\1110404宇博實業-芬園利民橋\\宇博彰化芬園鄉利民橋訂單分析表.xls",
      "detected_document_role": "spreadsheet_other",
      "file_sha256": "966BC22278A067F5F04A07B94BEC259C46C5F8024AF771FDED1C5957A518293F",
      "worksheet_name": "Sheet2",
      "worksheet_visibility": "visible",
      "worksheet_fingerprint": "6E1F00A07BA73F8D4F7DB68596FEFD5B44486D4E3BBD87FFD9346354C946519A",
      "proposed_decision": "CANDIDATE",
      "prefilter_state": "SUBMIT_TO_REVIEW",
      "reason_codes": [
        "CURRENT_PROJECT_ID_MATCH_REVIEWABLE",
        "LEGACY_XLS_PARSED_BY_EXCEL_COM_READ_ONLY",
        "MACROS_DISABLED"
      ],
      "checks": [
        {
          "check": "source_root",
          "status": "PASS",
          "evidence": "SRC-ALL-PROJECTS"
        },
        {
          "check": "file_sha256",
          "status": "PASS",
          "evidence": "966BC22278A067F5F04A07B94BEC259C46C5F8024AF771FDED1C5957A518293F"
        },
        {
          "check": "legacy_xls_parser_stability",
          "status": "PASS",
          "evidence": "excel_com_legacy_xls_v1"
        },
        {
          "check": "worksheet_fingerprint",
          "status": "PASS",
          "evidence": "6E1F00A07BA73F8D4F7DB68596FEFD5B44486D4E3BBD87FFD9346354C946519A"
        }
      ],
      "reviewable": true
    },
    {
      "decision_id": "SGD-316C6FFF77A62B",
      "file_id": "SRC-ALL-PROJECTS-FILE-969ACEDD72F3",
      "sheet_id": "SRC-ALL-PROJECTS-FILE-969ACEDD72F3-XLS-SHEET-002",
      "project_id": "1110404",
      "relative_path": "111年度工作\\111年度工作\\111年度訂單(已完成)\\1110404宇博實業-芬園利民橋\\宇博彰化芬園鄉利民橋訂單分析表.xls",
      "detected_document_role": "spreadsheet_other",
      "file_sha256": "966BC22278A067F5F04A07B94BEC259C46C5F8024AF771FDED1C5957A518293F",
      "worksheet_name": "Sheet3",
      "worksheet_visibility": "visible",
      "worksheet_fingerprint": "54A7F3467D202254816CDDA76C992CF40888AD969355429892E7625654B0F933",
      "proposed_decision": "CANDIDATE",
      "prefilter_state": "SUBMIT_TO_REVIEW",
      "reason_codes": [
        "CURRENT_PROJECT_ID_MATCH_REVIEWABLE",
        "LEGACY_XLS_PARSED_BY_EXCEL_COM_READ_ONLY",
        "MACROS_DISABLED"
      ],
      "checks": [
        {
          "check": "source_root",
          "status": "PASS",
          "evidence": "SRC-ALL-PROJECTS"
        },
        {
          "check": "file_sha256",
          "status": "PASS",
          "evidence": "966BC22278A067F5F04A07B94BEC259C46C5F8024AF771FDED1C5957A518293F"
        },
        {
          "check": "legacy_xls_parser_stability",
          "status": "PASS",
          "evidence": "excel_com_legacy_xls_v1"
        },
        {
          "check": "worksheet_fingerprint",
          "status": "PASS",
          "evidence": "54A7F3467D202254816CDDA76C992CF40888AD969355429892E7625654B0F933"
        }
      ],
      "reviewable": true
    },
    {
      "decision_id": "SGD-99A73FC2696D5E",
      "file_id": "SRC-ALL-PROJECTS-FILE-969ACEDD72F3",
      "sheet_id": "SRC-ALL-PROJECTS-FILE-969ACEDD72F3-XLS-SHEET-003",
      "project_id": "1110404",
      "relative_path": "111年度工作\\111年度工作\\111年度訂單(已完成)\\1110404宇博實業-芬園利民橋\\宇博彰化芬園鄉利民橋訂單分析表.xls",
      "detected_document_role": "spreadsheet_other",
      "file_sha256": "966BC22278A067F5F04A07B94BEC259C46C5F8024AF771FDED1C5957A518293F",
      "worksheet_name": "Sheet1",
      "worksheet_visibility": "visible",
      "worksheet_fingerprint": "D041E0793DF28BABB410316EB1776F89CA124C9C98B3B476B8B3A2A9A7C14D53",
      "proposed_decision": "CANDIDATE",
      "prefilter_state": "SUBMIT_TO_REVIEW",
      "reason_codes": [
        "CURRENT_PROJECT_ID_MATCH_REVIEWABLE",
        "LEGACY_XLS_PARSED_BY_EXCEL_COM_READ_ONLY",
        "MACROS_DISABLED"
      ],
      "checks": [
        {
          "check": "source_root",
          "status": "PASS",
          "evidence": "SRC-ALL-PROJECTS"
        },
        {
          "check": "file_sha256",
          "status": "PASS",
          "evidence": "966BC22278A067F5F04A07B94BEC259C46C5F8024AF771FDED1C5957A518293F"
        },
        {
          "check": "legacy_xls_parser_stability",
          "status": "PASS",
          "evidence": "excel_com_legacy_xls_v1"
        },
        {
          "check": "worksheet_fingerprint",
          "status": "PASS",
          "evidence": "D041E0793DF28BABB410316EB1776F89CA124C9C98B3B476B8B3A2A9A7C14D53"
        }
      ],
      "reviewable": true
    },
    {
      "decision_id": "SGD-154665F99F39D9",
      "file_id": "SRC-ALL-PROJECTS-FILE-CA81957454CE",
      "sheet_id": "SRC-ALL-PROJECTS-FILE-CA81957454CE-XLS-SHEET-001",
      "project_id": "1110404",
      "relative_path": "111年度工作\\111年度工作\\111年度訂單(已完成)\\1110404宇博實業-芬園利民橋\\宇博彰化芬園利民橋加壓站分項ls.xls",
      "detected_document_role": "spreadsheet_other",
      "file_sha256": "460ECF0ECB675D1D074665965459B57663D9B55FF25A1BB4356C135905A26A0A",
      "worksheet_name": "Sheet1",
      "worksheet_visibility": "visible",
      "worksheet_fingerprint": "04EDB5C3BE300BC47A0B02A868204E2332F009FC9FE0CED31484D66764ABA289",
      "proposed_decision": "CANDIDATE",
      "prefilter_state": "SUBMIT_TO_REVIEW",
      "reason_codes": [
        "CURRENT_PROJECT_ID_MATCH_REVIEWABLE",
        "LEGACY_XLS_PARSED_BY_EXCEL_COM_READ_ONLY",
        "MACROS_DISABLED"
      ],
      "checks": [
        {
          "check": "source_root",
          "status": "PASS",
          "evidence": "SRC-ALL-PROJECTS"
        },
        {
          "check": "file_sha256",
          "status": "PASS",
          "evidence": "460ECF0ECB675D1D074665965459B57663D9B55FF25A1BB4356C135905A26A0A"
        },
        {
          "check": "legacy_xls_parser_stability",
          "status": "PASS",
          "evidence": "excel_com_legacy_xls_v1"
        },
        {
          "check": "worksheet_fingerprint",
          "status": "PASS",
          "evidence": "04EDB5C3BE300BC47A0B02A868204E2332F009FC9FE0CED31484D66764ABA289"
        }
      ],
      "reviewable": true
    },
    {
      "decision_id": "SGD-58743B0E288D2F",
      "file_id": "SRC-ALL-PROJECTS-FILE-CA81957454CE",
      "sheet_id": "SRC-ALL-PROJECTS-FILE-CA81957454CE-XLS-SHEET-002",
      "project_id": "1110404",
      "relative_path": "111年度工作\\111年度工作\\111年度訂單(已完成)\\1110404宇博實業-芬園利民橋\\宇博彰化芬園利民橋加壓站分項ls.xls",
      "detected_document_role": "spreadsheet_other",
      "file_sha256": "460ECF0ECB675D1D074665965459B57663D9B55FF25A1BB4356C135905A26A0A",
      "worksheet_name": "Sheet2",
      "worksheet_visibility": "visible",
      "worksheet_fingerprint": "2327F3E6ECEE912E215AF094F55DE408AB2C6FEEB3ABDC7FD50B51592DA9CE91",
      "proposed_decision": "CANDIDATE",
      "prefilter_state": "SUBMIT_TO_REVIEW",
      "reason_codes": [
        "CURRENT_PROJECT_ID_MATCH_REVIEWABLE",
        "LEGACY_XLS_PARSED_BY_EXCEL_COM_READ_ONLY",
        "MACROS_DISABLED"
      ],
      "checks": [
        {
          "check": "source_root",
          "status": "PASS",
          "evidence": "SRC-ALL-PROJECTS"
        },
        {
          "check": "file_sha256",
          "status": "PASS",
          "evidence": "460ECF0ECB675D1D074665965459B57663D9B55FF25A1BB4356C135905A26A0A"
        },
        {
          "check": "legacy_xls_parser_stability",
          "status": "PASS",
          "evidence": "excel_com_legacy_xls_v1"
        },
        {
          "check": "worksheet_fingerprint",
          "status": "PASS",
          "evidence": "2327F3E6ECEE912E215AF094F55DE408AB2C6FEEB3ABDC7FD50B51592DA9CE91"
        }
      ],
      "reviewable": true
    },
    {
      "decision_id": "SGD-9FE56632926677",
      "file_id": "SRC-ALL-PROJECTS-FILE-CA81957454CE",
      "sheet_id": "SRC-ALL-PROJECTS-FILE-CA81957454CE-XLS-SHEET-003",
      "project_id": "1110404",
      "relative_path": "111年度工作\\111年度工作\\111年度訂單(已完成)\\1110404宇博實業-芬園利民橋\\宇博彰化芬園利民橋加壓站分項ls.xls",
      "detected_document_role": "spreadsheet_other",
      "file_sha256": "460ECF0ECB675D1D074665965459B57663D9B55FF25A1BB4356C135905A26A0A",
      "worksheet_name": "Sheet3",
      "worksheet_visibility": "visible",
      "worksheet_fingerprint": "54A7F3467D202254816CDDA76C992CF40888AD969355429892E7625654B0F933",
      "proposed_decision": "CANDIDATE",
      "prefilter_state": "SUBMIT_TO_REVIEW",
      "reason_codes": [
        "CURRENT_PROJECT_ID_MATCH_REVIEWABLE",
        "LEGACY_XLS_PARSED_BY_EXCEL_COM_READ_ONLY",
        "MACROS_DISABLED"
      ],
      "checks": [
        {
          "check": "source_root",
          "status": "PASS",
          "evidence": "SRC-ALL-PROJECTS"
        },
        {
          "check": "file_sha256",
          "status": "PASS",
          "evidence": "460ECF0ECB675D1D074665965459B57663D9B55FF25A1BB4356C135905A26A0A"
        },
        {
          "check": "legacy_xls_parser_stability",
          "status": "PASS",
          "evidence": "excel_com_legacy_xls_v1"
        },
        {
          "check": "worksheet_fingerprint",
          "status": "PASS",
          "evidence": "54A7F3467D202254816CDDA76C992CF40888AD969355429892E7625654B0F933"
        }
      ],
      "reviewable": true
    }
  ],
  "excluded_items": [
    {
      "decision_id": "SGD-1E92D26A6909CA",
      "file_id": "SRC-ALL-PROJECTS-FILE-9C7505CDBB38",
      "sheet_id": "SRC-ALL-PROJECTS-FILE-9C7505CDBB38-XLS-SHEET-001",
      "project_id": "1110404",
      "relative_path": "111年度工作\\111年度工作\\111年度訂單(已完成)\\1110404宇博實業-芬園利民橋\\宇博彰化芬園鄉利民橋加壓站合約審查表.xls",
      "detected_document_role": "allowed_contract_workbook",
      "file_sha256": "BB4A8FECCA3D1ED14D54FA6F9A3D0885F34D63160F23C585F6A0955750306501",
      "worksheet_name": "分析表",
      "worksheet_visibility": "visible",
      "worksheet_fingerprint": "39A2693D6D07CFD0CF67C1FB98B893FD015E57ABD38AC3222EBE360C847D0486",
      "proposed_decision": "QUARANTINED",
      "prefilter_state": "QUARANTINED",
      "reason_codes": [
        "CURRENT_PROJECT_ID_MATCH_REVIEWABLE",
        "LEGACY_XLS_PARSED_BY_EXCEL_COM_READ_ONLY",
        "MACROS_DISABLED",
        "NAMED_RANGE_PRESENT"
      ],
      "checks": [
        {
          "check": "source_root",
          "status": "PASS",
          "evidence": "SRC-ALL-PROJECTS"
        },
        {
          "check": "file_sha256",
          "status": "PASS",
          "evidence": "BB4A8FECCA3D1ED14D54FA6F9A3D0885F34D63160F23C585F6A0955750306501"
        },
        {
          "check": "legacy_xls_parser_stability",
          "status": "PASS",
          "evidence": "excel_com_legacy_xls_v1"
        },
        {
          "check": "worksheet_fingerprint",
          "status": "PASS",
          "evidence": "39A2693D6D07CFD0CF67C1FB98B893FD015E57ABD38AC3222EBE360C847D0486"
        }
      ],
      "reviewable": false
    },
    {
      "decision_id": "SGD-9C44A25763284B",
      "file_id": "SRC-ALL-PROJECTS-FILE-9C7505CDBB38",
      "sheet_id": "SRC-ALL-PROJECTS-FILE-9C7505CDBB38-XLS-SHEET-002",
      "project_id": "1110404",
      "relative_path": "111年度工作\\111年度工作\\111年度訂單(已完成)\\1110404宇博實業-芬園利民橋\\宇博彰化芬園鄉利民橋加壓站合約審查表.xls",
      "detected_document_role": "allowed_contract_workbook",
      "file_sha256": "BB4A8FECCA3D1ED14D54FA6F9A3D0885F34D63160F23C585F6A0955750306501",
      "worksheet_name": "會議審查",
      "worksheet_visibility": "visible",
      "worksheet_fingerprint": "0C7BA3AF42DCD0CC3D5CBC997B323C9A239748E558246F1671FBC29E5E9556D9",
      "proposed_decision": "QUARANTINED",
      "prefilter_state": "QUARANTINED",
      "reason_codes": [
        "CURRENT_PROJECT_ID_MATCH_REVIEWABLE",
        "LEGACY_XLS_PARSED_BY_EXCEL_COM_READ_ONLY",
        "MACROS_DISABLED",
        "NAMED_RANGE_PRESENT"
      ],
      "checks": [
        {
          "check": "source_root",
          "status": "PASS",
          "evidence": "SRC-ALL-PROJECTS"
        },
        {
          "check": "file_sha256",
          "status": "PASS",
          "evidence": "BB4A8FECCA3D1ED14D54FA6F9A3D0885F34D63160F23C585F6A0955750306501"
        },
        {
          "check": "legacy_xls_parser_stability",
          "status": "PASS",
          "evidence": "excel_com_legacy_xls_v1"
        },
        {
          "check": "worksheet_fingerprint",
          "status": "PASS",
          "evidence": "0C7BA3AF42DCD0CC3D5CBC997B323C9A239748E558246F1671FBC29E5E9556D9"
        }
      ],
      "reviewable": false
    },
    {
      "decision_id": "SGD-4A92E00143B376",
      "file_id": "SRC-ALL-PROJECTS-FILE-9C7505CDBB38",
      "sheet_id": "SRC-ALL-PROJECTS-FILE-9C7505CDBB38-XLS-SHEET-003",
      "project_id": "1110404",
      "relative_path": "111年度工作\\111年度工作\\111年度訂單(已完成)\\1110404宇博實業-芬園利民橋\\宇博彰化芬園鄉利民橋加壓站合約審查表.xls",
      "detected_document_role": "allowed_contract_workbook",
      "file_sha256": "BB4A8FECCA3D1ED14D54FA6F9A3D0885F34D63160F23C585F6A0955750306501",
      "worksheet_name": "Sheet3",
      "worksheet_visibility": "visible",
      "worksheet_fingerprint": "2431A7B5E34F6CDDF636CB6420EDAF96BB8F1E51757547FA6AD1B769DF2C82B2",
      "proposed_decision": "QUARANTINED",
      "prefilter_state": "QUARANTINED",
      "reason_codes": [
        "CURRENT_PROJECT_ID_MATCH_REVIEWABLE",
        "LEGACY_XLS_PARSED_BY_EXCEL_COM_READ_ONLY",
        "MACROS_DISABLED",
        "NAMED_RANGE_PRESENT"
      ],
      "checks": [
        {
          "check": "source_root",
          "status": "PASS",
          "evidence": "SRC-ALL-PROJECTS"
        },
        {
          "check": "file_sha256",
          "status": "PASS",
          "evidence": "BB4A8FECCA3D1ED14D54FA6F9A3D0885F34D63160F23C585F6A0955750306501"
        },
        {
          "check": "legacy_xls_parser_stability",
          "status": "PASS",
          "evidence": "excel_com_legacy_xls_v1"
        },
        {
          "check": "worksheet_fingerprint",
          "status": "PASS",
          "evidence": "2431A7B5E34F6CDDF636CB6420EDAF96BB8F1E51757547FA6AD1B769DF2C82B2"
        }
      ],
      "reviewable": false
    },
    {
      "decision_id": "SGD-DD318B0D6BDC85",
      "file_id": "SRC-ALL-PROJECTS-FILE-BAE592ED9C3A",
      "sheet_id": "SRC-ALL-PROJECTS-FILE-BAE592ED9C3A-XLS-SHEET-001",
      "project_id": "1110404",
      "relative_path": "111年度工作\\111年度工作\\111年度訂單(已完成)\\1110404宇博實業-芬園利民橋\\宇博彰化芬園鄉利民橋加壓站生產能力分析表.xls",
      "detected_document_role": "spreadsheet_other",
      "file_sha256": "976F802FF970BBE318FB2968310AB3A86C8804D08F9FA8255F9F9D1855743ED1",
      "worksheet_name": "分析表",
      "worksheet_visibility": "visible",
      "worksheet_fingerprint": "D82CF971A31DA4266E64495024A4FB5190441CB77EBF9472C69118F63D6144AC",
      "proposed_decision": "QUARANTINED",
      "prefilter_state": "QUARANTINED",
      "reason_codes": [
        "CURRENT_PROJECT_ID_MATCH_REVIEWABLE",
        "LEGACY_XLS_PARSED_BY_EXCEL_COM_READ_ONLY",
        "MACROS_DISABLED",
        "NAMED_RANGE_PRESENT"
      ],
      "checks": [
        {
          "check": "source_root",
          "status": "PASS",
          "evidence": "SRC-ALL-PROJECTS"
        },
        {
          "check": "file_sha256",
          "status": "PASS",
          "evidence": "976F802FF970BBE318FB2968310AB3A86C8804D08F9FA8255F9F9D1855743ED1"
        },
        {
          "check": "legacy_xls_parser_stability",
          "status": "PASS",
          "evidence": "excel_com_legacy_xls_v1"
        },
        {
          "check": "worksheet_fingerprint",
          "status": "PASS",
          "evidence": "D82CF971A31DA4266E64495024A4FB5190441CB77EBF9472C69118F63D6144AC"
        }
      ],
      "reviewable": false
    },
    {
      "decision_id": "SGD-B4CC5F1F4D8000",
      "file_id": "SRC-ALL-PROJECTS-FILE-BAE592ED9C3A",
      "sheet_id": "SRC-ALL-PROJECTS-FILE-BAE592ED9C3A-XLS-SHEET-002",
      "project_id": "1110404",
      "relative_path": "111年度工作\\111年度工作\\111年度訂單(已完成)\\1110404宇博實業-芬園利民橋\\宇博彰化芬園鄉利民橋加壓站生產能力分析表.xls",
      "detected_document_role": "spreadsheet_other",
      "file_sha256": "976F802FF970BBE318FB2968310AB3A86C8804D08F9FA8255F9F9D1855743ED1",
      "worksheet_name": "會議審查",
      "worksheet_visibility": "visible",
      "worksheet_fingerprint": "BBDD1D43247C07456A401D1B6444FE071E20394B3AC154B26CC8CACF5E951DB9",
      "proposed_decision": "QUARANTINED",
      "prefilter_state": "QUARANTINED",
      "reason_codes": [
        "CURRENT_PROJECT_ID_MATCH_REVIEWABLE",
        "LEGACY_XLS_PARSED_BY_EXCEL_COM_READ_ONLY",
        "MACROS_DISABLED",
        "NAMED_RANGE_PRESENT"
      ],
      "checks": [
        {
          "check": "source_root",
          "status": "PASS",
          "evidence": "SRC-ALL-PROJECTS"
        },
        {
          "check": "file_sha256",
          "status": "PASS",
          "evidence": "976F802FF970BBE318FB2968310AB3A86C8804D08F9FA8255F9F9D1855743ED1"
        },
        {
          "check": "legacy_xls_parser_stability",
          "status": "PASS",
          "evidence": "excel_com_legacy_xls_v1"
        },
        {
          "check": "worksheet_fingerprint",
          "status": "PASS",
          "evidence": "BBDD1D43247C07456A401D1B6444FE071E20394B3AC154B26CC8CACF5E951DB9"
        }
      ],
      "reviewable": false
    },
    {
      "decision_id": "SGD-FBE04F7E5C1D9F",
      "file_id": "SRC-ALL-PROJECTS-FILE-BAE592ED9C3A",
      "sheet_id": "SRC-ALL-PROJECTS-FILE-BAE592ED9C3A-XLS-SHEET-003",
      "project_id": "1110404",
      "relative_path": "111年度工作\\111年度工作\\111年度訂單(已完成)\\1110404宇博實業-芬園利民橋\\宇博彰化芬園鄉利民橋加壓站生產能力分析表.xls",
      "detected_document_role": "spreadsheet_other",
      "file_sha256": "976F802FF970BBE318FB2968310AB3A86C8804D08F9FA8255F9F9D1855743ED1",
      "worksheet_name": "Sheet3",
      "worksheet_visibility": "visible",
      "worksheet_fingerprint": "2431A7B5E34F6CDDF636CB6420EDAF96BB8F1E51757547FA6AD1B769DF2C82B2",
      "proposed_decision": "QUARANTINED",
      "prefilter_state": "QUARANTINED",
      "reason_codes": [
        "CURRENT_PROJECT_ID_MATCH_REVIEWABLE",
        "LEGACY_XLS_PARSED_BY_EXCEL_COM_READ_ONLY",
        "MACROS_DISABLED",
        "NAMED_RANGE_PRESENT"
      ],
      "checks": [
        {
          "check": "source_root",
          "status": "PASS",
          "evidence": "SRC-ALL-PROJECTS"
        },
        {
          "check": "file_sha256",
          "status": "PASS",
          "evidence": "976F802FF970BBE318FB2968310AB3A86C8804D08F9FA8255F9F9D1855743ED1"
        },
        {
          "check": "legacy_xls_parser_stability",
          "status": "PASS",
          "evidence": "excel_com_legacy_xls_v1"
        },
        {
          "check": "worksheet_fingerprint",
          "status": "PASS",
          "evidence": "2431A7B5E34F6CDDF636CB6420EDAF96BB8F1E51757547FA6AD1B769DF2C82B2"
        }
      ],
      "reviewable": false
    },
    {
      "decision_id": "SGD-41EF350A34D739",
      "file_id": "SRC-ALL-PROJECTS-FILE-D2FD564B8814",
      "sheet_id": "SRC-ALL-PROJECTS-FILE-D2FD564B8814-XLS-SHEET-001",
      "project_id": "1110404",
      "relative_path": "111年度工作\\111年度工作\\111年度訂單(已完成)\\1110404宇博實業-芬園利民橋\\工作記錄單宇博彰化芬園利民橋加壓站s.xls",
      "detected_document_role": "spreadsheet_other",
      "file_sha256": "EC9EE04D8F60269FA08B2B18A186655F303B205B898A328A21BA26FD66D423D3",
      "worksheet_name": "0413",
      "worksheet_visibility": "visible",
      "worksheet_fingerprint": "44B250AE62DD3B0BC927C3C0EBF31D46567F1342287E2EFDFBA771BAAA7F9D65",
      "proposed_decision": "QUARANTINED",
      "prefilter_state": "QUARANTINED",
      "reason_codes": [
        "CURRENT_PROJECT_ID_MATCH_REVIEWABLE",
        "LEGACY_XLS_PARSED_BY_EXCEL_COM_READ_ONLY",
        "MACROS_DISABLED",
        "NAMED_RANGE_PRESENT"
      ],
      "checks": [
        {
          "check": "source_root",
          "status": "PASS",
          "evidence": "SRC-ALL-PROJECTS"
        },
        {
          "check": "file_sha256",
          "status": "PASS",
          "evidence": "EC9EE04D8F60269FA08B2B18A186655F303B205B898A328A21BA26FD66D423D3"
        },
        {
          "check": "legacy_xls_parser_stability",
          "status": "PASS",
          "evidence": "excel_com_legacy_xls_v1"
        },
        {
          "check": "worksheet_fingerprint",
          "status": "PASS",
          "evidence": "44B250AE62DD3B0BC927C3C0EBF31D46567F1342287E2EFDFBA771BAAA7F9D65"
        }
      ],
      "reviewable": false
    },
    {
      "decision_id": "SGD-41C59E198051F5",
      "file_id": "SRC-ALL-PROJECTS-FILE-D2FD564B8814",
      "sheet_id": "SRC-ALL-PROJECTS-FILE-D2FD564B8814-XLS-SHEET-002",
      "project_id": "1110404",
      "relative_path": "111年度工作\\111年度工作\\111年度訂單(已完成)\\1110404宇博實業-芬園利民橋\\工作記錄單宇博彰化芬園利民橋加壓站s.xls",
      "detected_document_role": "spreadsheet_other",
      "file_sha256": "EC9EE04D8F60269FA08B2B18A186655F303B205B898A328A21BA26FD66D423D3",
      "worksheet_name": "0415",
      "worksheet_visibility": "visible",
      "worksheet_fingerprint": "80F99AC9C6518B1C241192861715CA6A227CACBF8E8B08CB512EBB3C660380EC",
      "proposed_decision": "QUARANTINED",
      "prefilter_state": "QUARANTINED",
      "reason_codes": [
        "CURRENT_PROJECT_ID_MATCH_REVIEWABLE",
        "LEGACY_XLS_PARSED_BY_EXCEL_COM_READ_ONLY",
        "MACROS_DISABLED",
        "NAMED_RANGE_PRESENT"
      ],
      "checks": [
        {
          "check": "source_root",
          "status": "PASS",
          "evidence": "SRC-ALL-PROJECTS"
        },
        {
          "check": "file_sha256",
          "status": "PASS",
          "evidence": "EC9EE04D8F60269FA08B2B18A186655F303B205B898A328A21BA26FD66D423D3"
        },
        {
          "check": "legacy_xls_parser_stability",
          "status": "PASS",
          "evidence": "excel_com_legacy_xls_v1"
        },
        {
          "check": "worksheet_fingerprint",
          "status": "PASS",
          "evidence": "80F99AC9C6518B1C241192861715CA6A227CACBF8E8B08CB512EBB3C660380EC"
        }
      ],
      "reviewable": false
    },
    {
      "decision_id": "SGD-311A2A3D5DBAD0",
      "file_id": "SRC-ALL-PROJECTS-FILE-D2FD564B8814",
      "sheet_id": "SRC-ALL-PROJECTS-FILE-D2FD564B8814-XLS-SHEET-003",
      "project_id": "1110404",
      "relative_path": "111年度工作\\111年度工作\\111年度訂單(已完成)\\1110404宇博實業-芬園利民橋\\工作記錄單宇博彰化芬園利民橋加壓站s.xls",
      "detected_document_role": "spreadsheet_other",
      "file_sha256": "EC9EE04D8F60269FA08B2B18A186655F303B205B898A328A21BA26FD66D423D3",
      "worksheet_name": "空白",
      "worksheet_visibility": "visible",
      "worksheet_fingerprint": "B5AD89DF08DECDCE5F994AD3DA7C3BBEA1E45E17C3F9FE8E167667935B3A6262",
      "proposed_decision": "QUARANTINED",
      "prefilter_state": "QUARANTINED",
      "reason_codes": [
        "CURRENT_PROJECT_ID_MATCH_REVIEWABLE",
        "LEGACY_XLS_PARSED_BY_EXCEL_COM_READ_ONLY",
        "MACROS_DISABLED",
        "NAMED_RANGE_PRESENT"
      ],
      "checks": [
        {
          "check": "source_root",
          "status": "PASS",
          "evidence": "SRC-ALL-PROJECTS"
        },
        {
          "check": "file_sha256",
          "status": "PASS",
          "evidence": "EC9EE04D8F60269FA08B2B18A186655F303B205B898A328A21BA26FD66D423D3"
        },
        {
          "check": "legacy_xls_parser_stability",
          "status": "PASS",
          "evidence": "excel_com_legacy_xls_v1"
        },
        {
          "check": "worksheet_fingerprint",
          "status": "PASS",
          "evidence": "B5AD89DF08DECDCE5F994AD3DA7C3BBEA1E45E17C3F9FE8E167667935B3A6262"
        }
      ],
      "reviewable": false
    },
    {
      "decision_id": "SGD-7C4A3DEC7F2D75",
      "file_id": "SRC-ALL-PROJECTS-FILE-D2FD564B8814",
      "sheet_id": "SRC-ALL-PROJECTS-FILE-D2FD564B8814-XLS-SHEET-004",
      "project_id": "1110404",
      "relative_path": "111年度工作\\111年度工作\\111年度訂單(已完成)\\1110404宇博實業-芬園利民橋\\工作記錄單宇博彰化芬園利民橋加壓站s.xls",
      "detected_document_role": "spreadsheet_other",
      "file_sha256": "EC9EE04D8F60269FA08B2B18A186655F303B205B898A328A21BA26FD66D423D3",
      "worksheet_name": "05",
      "worksheet_visibility": "visible",
      "worksheet_fingerprint": "C486E895C071C0C972EC1931CBA0899016DCFC94173F74D32DAB9D6E9DFCD142",
      "proposed_decision": "QUARANTINED",
      "prefilter_state": "QUARANTINED",
      "reason_codes": [
        "CURRENT_PROJECT_ID_MATCH_REVIEWABLE",
        "LEGACY_XLS_PARSED_BY_EXCEL_COM_READ_ONLY",
        "MACROS_DISABLED",
        "NAMED_RANGE_PRESENT"
      ],
      "checks": [
        {
          "check": "source_root",
          "status": "PASS",
          "evidence": "SRC-ALL-PROJECTS"
        },
        {
          "check": "file_sha256",
          "status": "PASS",
          "evidence": "EC9EE04D8F60269FA08B2B18A186655F303B205B898A328A21BA26FD66D423D3"
        },
        {
          "check": "legacy_xls_parser_stability",
          "status": "PASS",
          "evidence": "excel_com_legacy_xls_v1"
        },
        {
          "check": "worksheet_fingerprint",
          "status": "PASS",
          "evidence": "C486E895C071C0C972EC1931CBA0899016DCFC94173F74D32DAB9D6E9DFCD142"
        }
      ],
      "reviewable": false
    },
    {
      "decision_id": "SGD-A9E0910F377360",
      "file_id": "SRC-ALL-PROJECTS-FILE-D2FD564B8814",
      "sheet_id": "SRC-ALL-PROJECTS-FILE-D2FD564B8814-XLS-SHEET-005",
      "project_id": "1110404",
      "relative_path": "111年度工作\\111年度工作\\111年度訂單(已完成)\\1110404宇博實業-芬園利民橋\\工作記錄單宇博彰化芬園利民橋加壓站s.xls",
      "detected_document_role": "spreadsheet_other",
      "file_sha256": "EC9EE04D8F60269FA08B2B18A186655F303B205B898A328A21BA26FD66D423D3",
      "worksheet_name": "05 (2)",
      "worksheet_visibility": "visible",
      "worksheet_fingerprint": "AB9BB32E176B865C84DBA725CE82266BEFF1495F0C2BAF3232E972E6C74BD8B2",
      "proposed_decision": "QUARANTINED",
      "prefilter_state": "QUARANTINED",
      "reason_codes": [
        "CURRENT_PROJECT_ID_MATCH_REVIEWABLE",
        "LEGACY_XLS_PARSED_BY_EXCEL_COM_READ_ONLY",
        "MACROS_DISABLED",
        "NAMED_RANGE_PRESENT"
      ],
      "checks": [
        {
          "check": "source_root",
          "status": "PASS",
          "evidence": "SRC-ALL-PROJECTS"
        },
        {
          "check": "file_sha256",
          "status": "PASS",
          "evidence": "EC9EE04D8F60269FA08B2B18A186655F303B205B898A328A21BA26FD66D423D3"
        },
        {
          "check": "legacy_xls_parser_stability",
          "status": "PASS",
          "evidence": "excel_com_legacy_xls_v1"
        },
        {
          "check": "worksheet_fingerprint",
          "status": "PASS",
          "evidence": "AB9BB32E176B865C84DBA725CE82266BEFF1495F0C2BAF3232E972E6C74BD8B2"
        }
      ],
      "reviewable": false
    },
    {
      "decision_id": "SGD-10AC93C56877A3",
      "file_id": "SRC-ALL-PROJECTS-FILE-D2FD564B8814",
      "sheet_id": "SRC-ALL-PROJECTS-FILE-D2FD564B8814-XLS-SHEET-006",
      "project_id": "1110404",
      "relative_path": "111年度工作\\111年度工作\\111年度訂單(已完成)\\1110404宇博實業-芬園利民橋\\工作記錄單宇博彰化芬園利民橋加壓站s.xls",
      "detected_document_role": "spreadsheet_other",
      "file_sha256": "EC9EE04D8F60269FA08B2B18A186655F303B205B898A328A21BA26FD66D423D3",
      "worksheet_name": "0505",
      "worksheet_visibility": "visible",
      "worksheet_fingerprint": "37D59563AEC62339E44CB44F1CDCF9876664CAEA847C43C2B551E73D1ADA7D27",
      "proposed_decision": "QUARANTINED",
      "prefilter_state": "QUARANTINED",
      "reason_codes": [
        "CURRENT_PROJECT_ID_MATCH_REVIEWABLE",
        "LEGACY_XLS_PARSED_BY_EXCEL_COM_READ_ONLY",
        "MACROS_DISABLED",
        "NAMED_RANGE_PRESENT"
      ],
      "checks": [
        {
          "check": "source_root",
          "status": "PASS",
          "evidence": "SRC-ALL-PROJECTS"
        },
        {
          "check": "file_sha256",
          "status": "PASS",
          "evidence": "EC9EE04D8F60269FA08B2B18A186655F303B205B898A328A21BA26FD66D423D3"
        },
        {
          "check": "legacy_xls_parser_stability",
          "status": "PASS",
          "evidence": "excel_com_legacy_xls_v1"
        },
        {
          "check": "worksheet_fingerprint",
          "status": "PASS",
          "evidence": "37D59563AEC62339E44CB44F1CDCF9876664CAEA847C43C2B551E73D1ADA7D27"
        }
      ],
      "reviewable": false
    }
  ]
}
